[
  {
    "Dawat The Live Kitchen": {
      " url ": "https://www.zomato.com/ncr/dawat-the-live-kitchen-sector-37-gurgaon",
      " location ": " SCO-77, Sector-10 A, Near Sector 37, Gurgaon",
      " rating ": [
        "3.6",
        "3.4"
      ],
      " facility ": [],
      " cuisines ": [
        "Mughlai",
        "Chinese",
        "North Indian"
      ],
      " cost_for_two ": "600",
      " hour ": "11am \u2013 11pm (Mon-Sun)",
      " featured ": [],
      " discount ": [
        "10% off on all orders above \u20b999"
      ]
    }
  },
  {
    "Dawat The Live Kitchen": {
      " url ": "https://www.zomato.com/ncr/dawat-the-live-kitchen-sector-37-gurgaon",
      " location ": " SCO-77, Sector-10 A, Near Sector 37, Gurgaon",
      " rating ": [
        "3.6",
        "3.4"
      ],
      " facility ": [],
      " cuisines ": [
        "Mughlai",
        "Chinese",
        "North Indian"
      ],
      " cost_for_two ": "600",
      " hour ": "11am \u2013 11pm (Mon-Sun)",
      " featured ": [],
      " discount ": [
        "10% off on all orders above \u20b999"
      ]
    },
    "Aakib Chickan Point": {
      " url ": "https://www.zomato.com/ncr/aakib-chickan-point-south-extension-2-new-delhi",
      " location ": " 436, Leela Ram Market, Masjid Moth, South Extension 2, New Delhi",
      " rating ": [
        "3.2",
        "4.1"
      ],
      " facility ": [],
      " cuisines ": [
        "Biryani"
      ],
      " cost_for_two ": "250",
      " hour ": "11am \u2013 8pm (Mon-Sun)",
      " featured ": [],
      " discount ": [
        "no discount"
      ]
    }
  },
  {
    "Dawat The Live Kitchen": {
      " url ": "https://www.zomato.com/ncr/dawat-the-live-kitchen-sector-37-gurgaon",
      " location ": " SCO-77, Sector-10 A, Near Sector 37, Gurgaon",
      " rating ": [
        "3.6",
        "3.4"
      ],
      " facility ": [],
      " cuisines ": [
        "Mughlai",
        "Chinese",
        "North Indian"
      ],
      " cost_for_two ": "600",
      " hour ": "11am \u2013 11pm (Mon-Sun)",
      " featured ": [],
      " discount ": [
        "10% off on all orders above \u20b999"
      ]
    },
    "Aakib Chickan Point": {
      " url ": "https://www.zomato.com/ncr/aakib-chickan-point-south-extension-2-new-delhi",
      " location ": " 436, Leela Ram Market, Masjid Moth, South Extension 2, New Delhi",
      " rating ": [
        "3.2",
        "4.1"
      ],
      " facility ": [],
      " cuisines ": [
        "Biryani"
      ],
      " cost_for_two ": "250",
      " hour ": "11am \u2013 8pm (Mon-Sun)",
      " featured ": [],
      " discount ": [
        "no discount"
      ]
    },
    "Order Cake Online": {
      " url ": "https://www.zomato.com/ncr/order-cake-online-2-palam-new-delhi",
      " location ": " WZ 507A, Opposite Dwarka Flyover, Pillar 59, Palam Colony, Palam, New Delhi",
      " rating ": [
        "3.3"
      ],
      " facility ": [],
      " cuisines ": [
        "Bakery",
        "Desserts"
      ],
      " cost_for_two ": "300",
      " hour ": "10am \u2013 10pm (Mon-Sun)",
      " featured ": [],
      " discount ": [
        "15% off on all orders above \u20b9300"
      ]
    }
  },
  {
    "Dawat The Live Kitchen": {
      " url ": "https://www.zomato.com/ncr/dawat-the-live-kitchen-sector-37-gurgaon",
      " location ": " SCO-77, Sector-10 A, Near Sector 37, Gurgaon",
      " rating ": [
        "3.6",
        "3.4"
      ],
      " facility ": [],
      " cuisines ": [
        "Mughlai",
        "Chinese",
        "North Indian"
      ],
      " cost_for_two ": "600",
      " hour ": "11am \u2013 11pm (Mon-Sun)",
      " featured ": [],
      " discount ": [
        "10% off on all orders above \u20b999"
      ]
    },
    "Aakib Chickan Point": {
      " url ": "https://www.zomato.com/ncr/aakib-chickan-point-south-extension-2-new-delhi",
      " location ": " 436, Leela Ram Market, Masjid Moth, South Extension 2, New Delhi",
      " rating ": [
        "3.2",
        "4.1"
      ],
      " facility ": [],
      " cuisines ": [
        "Biryani"
      ],
      " cost_for_two ": "250",
      " hour ": "11am \u2013 8pm (Mon-Sun)",
      " featured ": [],
      " discount ": [
        "no discount"
      ]
    },
    "Order Cake Online": {
      " url ": "https://www.zomato.com/ncr/order-cake-online-2-palam-new-delhi",
      " location ": " WZ 507A, Opposite Dwarka Flyover, Pillar 59, Palam Colony, Palam, New Delhi",
      " rating ": [
        "3.3"
      ],
      " facility ": [],
      " cuisines ": [
        "Bakery",
        "Desserts"
      ],
      " cost_for_two ": "300",
      " hour ": "10am \u2013 10pm (Mon-Sun)",
      " featured ": [],
      " discount ": [
        "15% off on all orders above \u20b9300"
      ]
    },
    "OM Food Plaza": {
      " url ": "https://www.zomato.com/ncr/om-food-plaza-zeta-1-greater-noida",
      " location ": " Shop A 17, AVJ Hights, Zeta 1, Greater Noida",
      " rating ": [
        "3.2",
        "3.3"
      ],
      " facility ": [],
      " cuisines ": [
        "North Indian",
        "Chinese"
      ],
      " cost_for_two ": "250",
      " hour ": "10am \u2013 10pm (Mon-Sun)",
      " featured ": [],
      " discount ": [
        "no discount"
      ]
    }
  },
  {
    "Dawat The Live Kitchen": {
      " url ": "https://www.zomato.com/ncr/dawat-the-live-kitchen-sector-37-gurgaon",
      " location ": " SCO-77, Sector-10 A, Near Sector 37, Gurgaon",
      " rating ": [
        "3.6",
        "3.4"
      ],
      " facility ": [],
      " cuisines ": [
        "Mughlai",
        "Chinese",
        "North Indian"
      ],
      " cost_for_two ": "600",
      " hour ": "11am \u2013 11pm (Mon-Sun)",
      " featured ": [],
      " discount ": [
        "10% off on all orders above \u20b999"
      ]
    },
    "Aakib Chickan Point": {
      " url ": "https://www.zomato.com/ncr/aakib-chickan-point-south-extension-2-new-delhi",
      " location ": " 436, Leela Ram Market, Masjid Moth, South Extension 2, New Delhi",
      " rating ": [
        "3.2",
        "4.1"
      ],
      " facility ": [],
      " cuisines ": [
        "Biryani"
      ],
      " cost_for_two ": "250",
      " hour ": "11am \u2013 8pm (Mon-Sun)",
      " featured ": [],
      " discount ": [
        "no discount"
      ]
    },
    "Order Cake Online": {
      " url ": "https://www.zomato.com/ncr/order-cake-online-2-palam-new-delhi",
      " location ": " WZ 507A, Opposite Dwarka Flyover, Pillar 59, Palam Colony, Palam, New Delhi",
      " rating ": [
        "3.3"
      ],
      " facility ": [],
      " cuisines ": [
        "Bakery",
        "Desserts"
      ],
      " cost_for_two ": "300",
      " hour ": "10am \u2013 10pm (Mon-Sun)",
      " featured ": [],
      " discount ": [
        "15% off on all orders above \u20b9300"
      ]
    },
    "OM Food Plaza": {
      " url ": "https://www.zomato.com/ncr/om-food-plaza-zeta-1-greater-noida",
      " location ": " Shop A 17, AVJ Hights, Zeta 1, Greater Noida",
      " rating ": [
        "3.2",
        "3.3"
      ],
      " facility ": [],
      " cuisines ": [
        "North Indian",
        "Chinese"
      ],
      " cost_for_two ": "250",
      " hour ": "10am \u2013 10pm (Mon-Sun)",
      " featured ": [],
      " discount ": [
        "no discount"
      ]
    },
    "Rahul Food Court": {
      " url ": "https://www.zomato.com/ncr/rahul-food-court-sector-37-gurgaon",
      " location ": " Shop 208/18, Khandsa Road, Opposite DAV School, Near Sector 37, Gurgaon",
      " rating ": [
        "3.1"
      ],
      " facility ": [],
      " cuisines ": [
        "South Indian",
        "North Indian"
      ],
      " cost_for_two ": "200",
      " hour ": "11am \u2013 11pm (Mon-Sun)",
      " featured ": [],
      " discount ": [
        "no discount"
      ]
    }
  },
  {
    "Dawat The Live Kitchen": {
      " url ": "https://www.zomato.com/ncr/dawat-the-live-kitchen-sector-37-gurgaon",
      " location ": " SCO-77, Sector-10 A, Near Sector 37, Gurgaon",
      " rating ": [
        "3.6",
        "3.4"
      ],
      " facility ": [],
      " cuisines ": [
        "Mughlai",
        "Chinese",
        "North Indian"
      ],
      " cost_for_two ": "600",
      " hour ": "11am \u2013 11pm (Mon-Sun)",
      " featured ": [],
      " discount ": [
        "10% off on all orders above \u20b999"
      ]
    },
    "Aakib Chickan Point": {
      " url ": "https://www.zomato.com/ncr/aakib-chickan-point-south-extension-2-new-delhi",
      " location ": " 436, Leela Ram Market, Masjid Moth, South Extension 2, New Delhi",
      " rating ": [
        "3.2",
        "4.1"
      ],
      " facility ": [],
      " cuisines ": [
        "Biryani"
      ],
      " cost_for_two ": "250",
      " hour ": "11am \u2013 8pm (Mon-Sun)",
      " featured ": [],
      " discount ": [
        "no discount"
      ]
    },
    "Order Cake Online": {
      " url ": "https://www.zomato.com/ncr/order-cake-online-2-palam-new-delhi",
      " location ": " WZ 507A, Opposite Dwarka Flyover, Pillar 59, Palam Colony, Palam, New Delhi",
      " rating ": [
        "3.3"
      ],
      " facility ": [],
      " cuisines ": [
        "Bakery",
        "Desserts"
      ],
      " cost_for_two ": "300",
      " hour ": "10am \u2013 10pm (Mon-Sun)",
      " featured ": [],
      " discount ": [
        "15% off on all orders above \u20b9300"
      ]
    },
    "OM Food Plaza": {
      " url ": "https://www.zomato.com/ncr/om-food-plaza-zeta-1-greater-noida",
      " location ": " Shop A 17, AVJ Hights, Zeta 1, Greater Noida",
      " rating ": [
        "3.2",
        "3.3"
      ],
      " facility ": [],
      " cuisines ": [
        "North Indian",
        "Chinese"
      ],
      " cost_for_two ": "250",
      " hour ": "10am \u2013 10pm (Mon-Sun)",
      " featured ": [],
      " discount ": [
        "no discount"
      ]
    },
    "Rahul Food Court": {
      " url ": "https://www.zomato.com/ncr/rahul-food-court-sector-37-gurgaon",
      " location ": " Shop 208/18, Khandsa Road, Opposite DAV School, Near Sector 37, Gurgaon",
      " rating ": [
        "3.1"
      ],
      " facility ": [],
      " cuisines ": [
        "South Indian",
        "North Indian"
      ],
      " cost_for_two ": "200",
      " hour ": "11am \u2013 11pm (Mon-Sun)",
      " featured ": [],
      " discount ": [
        "no discount"
      ]
    },
    "Samrat The Cake Shoppe": {
      " url ": "https://www.zomato.com/ncr/samrat-the-cake-shoppe-old-railway-road-gurgaon",
      " location ": " Sohna Chowk, Old Railway Road, Gurgaon",
      " rating ": [
        "2.7"
      ],
      " facility ": [],
      " cuisines ": [
        "Bakery",
        "Mithai",
        "Desserts",
        "Street Food",
        "Fast Food"
      ],
      " cost_for_two ": "300",
      " hour ": "8am \u2013 10:30pm (Mon-Sun)",
      " featured ": [],
      " discount ": [
        "no discount"
      ]
    }
  },
  {
    "Dawat The Live Kitchen": {
      " url ": "https://www.zomato.com/ncr/dawat-the-live-kitchen-sector-37-gurgaon",
      " location ": " SCO-77, Sector-10 A, Near Sector 37, Gurgaon",
      " rating ": [
        "3.6",
        "3.4"
      ],
      " facility ": [],
      " cuisines ": [
        "Mughlai",
        "Chinese",
        "North Indian"
      ],
      " cost_for_two ": "600",
      " hour ": "11am \u2013 11pm (Mon-Sun)",
      " featured ": [],
      " discount ": [
        "10% off on all orders above \u20b999"
      ]
    },
    "Aakib Chickan Point": {
      " url ": "https://www.zomato.com/ncr/aakib-chickan-point-south-extension-2-new-delhi",
      " location ": " 436, Leela Ram Market, Masjid Moth, South Extension 2, New Delhi",
      " rating ": [
        "3.2",
        "4.1"
      ],
      " facility ": [],
      " cuisines ": [
        "Biryani"
      ],
      " cost_for_two ": "250",
      " hour ": "11am \u2013 8pm (Mon-Sun)",
      " featured ": [],
      " discount ": [
        "no discount"
      ]
    },
    "Order Cake Online": {
      " url ": "https://www.zomato.com/ncr/order-cake-online-2-palam-new-delhi",
      " location ": " WZ 507A, Opposite Dwarka Flyover, Pillar 59, Palam Colony, Palam, New Delhi",
      " rating ": [
        "3.3"
      ],
      " facility ": [],
      " cuisines ": [
        "Bakery",
        "Desserts"
      ],
      " cost_for_two ": "300",
      " hour ": "10am \u2013 10pm (Mon-Sun)",
      " featured ": [],
      " discount ": [
        "15% off on all orders above \u20b9300"
      ]
    },
    "OM Food Plaza": {
      " url ": "https://www.zomato.com/ncr/om-food-plaza-zeta-1-greater-noida",
      " location ": " Shop A 17, AVJ Hights, Zeta 1, Greater Noida",
      " rating ": [
        "3.2",
        "3.3"
      ],
      " facility ": [],
      " cuisines ": [
        "North Indian",
        "Chinese"
      ],
      " cost_for_two ": "250",
      " hour ": "10am \u2013 10pm (Mon-Sun)",
      " featured ": [],
      " discount ": [
        "no discount"
      ]
    },
    "Rahul Food Court": {
      " url ": "https://www.zomato.com/ncr/rahul-food-court-sector-37-gurgaon",
      " location ": " Shop 208/18, Khandsa Road, Opposite DAV School, Near Sector 37, Gurgaon",
      " rating ": [
        "3.1"
      ],
      " facility ": [],
      " cuisines ": [
        "South Indian",
        "North Indian"
      ],
      " cost_for_two ": "200",
      " hour ": "11am \u2013 11pm (Mon-Sun)",
      " featured ": [],
      " discount ": [
        "no discount"
      ]
    },
    "Samrat The Cake Shoppe": {
      " url ": "https://www.zomato.com/ncr/samrat-the-cake-shoppe-old-railway-road-gurgaon",
      " location ": " Sohna Chowk, Old Railway Road, Gurgaon",
      " rating ": [
        "2.7"
      ],
      " facility ": [],
      " cuisines ": [
        "Bakery",
        "Mithai",
        "Desserts",
        "Street Food",
        "Fast Food"
      ],
      " cost_for_two ": "300",
      " hour ": "8am \u2013 10:30pm (Mon-Sun)",
      " featured ": [],
      " discount ": [
        "no discount"
      ]
    },
    "Sanjay Chicken Corner": {
      " url ": "https://www.zomato.com/ncr/sanjay-chicken-corner-nangloi-new-delhi",
      " location ": " 325, Plot C-26A, Khasra 6472, Chandan Vihar, Near Aata Chakki, Nihal Vihar, Phase 2, Nangloi, New Delhi",
      " rating ": [
        "3.4",
        "3.2"
      ],
      " facility ": [],
      " cuisines ": [
        "Fast Food"
      ],
      " cost_for_two ": "400",
      " hour ": "4pm \u2013 12midnight (Mon-Sun)",
      " featured ": [],
      " discount ": [
        "no discount"
      ]
    }
  },
  {
    "Dawat The Live Kitchen": {
      " url ": "https://www.zomato.com/ncr/dawat-the-live-kitchen-sector-37-gurgaon",
      " location ": " SCO-77, Sector-10 A, Near Sector 37, Gurgaon",
      " rating ": [
        "3.6",
        "3.4"
      ],
      " facility ": [],
      " cuisines ": [
        "Mughlai",
        "Chinese",
        "North Indian"
      ],
      " cost_for_two ": "600",
      " hour ": "11am \u2013 11pm (Mon-Sun)",
      " featured ": [],
      " discount ": [
        "10% off on all orders above \u20b999"
      ]
    },
    "Aakib Chickan Point": {
      " url ": "https://www.zomato.com/ncr/aakib-chickan-point-south-extension-2-new-delhi",
      " location ": " 436, Leela Ram Market, Masjid Moth, South Extension 2, New Delhi",
      " rating ": [
        "3.2",
        "4.1"
      ],
      " facility ": [],
      " cuisines ": [
        "Biryani"
      ],
      " cost_for_two ": "250",
      " hour ": "11am \u2013 8pm (Mon-Sun)",
      " featured ": [],
      " discount ": [
        "no discount"
      ]
    },
    "Order Cake Online": {
      " url ": "https://www.zomato.com/ncr/order-cake-online-2-palam-new-delhi",
      " location ": " WZ 507A, Opposite Dwarka Flyover, Pillar 59, Palam Colony, Palam, New Delhi",
      " rating ": [
        "3.3"
      ],
      " facility ": [],
      " cuisines ": [
        "Bakery",
        "Desserts"
      ],
      " cost_for_two ": "300",
      " hour ": "10am \u2013 10pm (Mon-Sun)",
      " featured ": [],
      " discount ": [
        "15% off on all orders above \u20b9300"
      ]
    },
    "OM Food Plaza": {
      " url ": "https://www.zomato.com/ncr/om-food-plaza-zeta-1-greater-noida",
      " location ": " Shop A 17, AVJ Hights, Zeta 1, Greater Noida",
      " rating ": [
        "3.2",
        "3.3"
      ],
      " facility ": [],
      " cuisines ": [
        "North Indian",
        "Chinese"
      ],
      " cost_for_two ": "250",
      " hour ": "10am \u2013 10pm (Mon-Sun)",
      " featured ": [],
      " discount ": [
        "no discount"
      ]
    },
    "Rahul Food Court": {
      " url ": "https://www.zomato.com/ncr/rahul-food-court-sector-37-gurgaon",
      " location ": " Shop 208/18, Khandsa Road, Opposite DAV School, Near Sector 37, Gurgaon",
      " rating ": [
        "3.1"
      ],
      " facility ": [],
      " cuisines ": [
        "South Indian",
        "North Indian"
      ],
      " cost_for_two ": "200",
      " hour ": "11am \u2013 11pm (Mon-Sun)",
      " featured ": [],
      " discount ": [
        "no discount"
      ]
    },
    "Samrat The Cake Shoppe": {
      " url ": "https://www.zomato.com/ncr/samrat-the-cake-shoppe-old-railway-road-gurgaon",
      " location ": " Sohna Chowk, Old Railway Road, Gurgaon",
      " rating ": [
        "2.7"
      ],
      " facility ": [],
      " cuisines ": [
        "Bakery",
        "Mithai",
        "Desserts",
        "Street Food",
        "Fast Food"
      ],
      " cost_for_two ": "300",
      " hour ": "8am \u2013 10:30pm (Mon-Sun)",
      " featured ": [],
      " discount ": [
        "no discount"
      ]
    },
    "Sanjay Chicken Corner": {
      " url ": "https://www.zomato.com/ncr/sanjay-chicken-corner-nangloi-new-delhi",
      " location ": " 325, Plot C-26A, Khasra 6472, Chandan Vihar, Near Aata Chakki, Nihal Vihar, Phase 2, Nangloi, New Delhi",
      " rating ": [
        "3.4",
        "3.2"
      ],
      " facility ": [],
      " cuisines ": [
        "Fast Food"
      ],
      " cost_for_two ": "400",
      " hour ": "4pm \u2013 12midnight (Mon-Sun)",
      " featured ": [],
      " discount ": [
        "no discount"
      ]
    },
    "The Friends' Republic": {
      " url ": "https://www.zomato.com/ncr/the-friends-republic-dlf-phase-5-gurgaon",
      " location ": " Opposite Paras Hospital, St. Thomas Marg, Sector 53, DLF Phase 5, Gurgaon",
      " rating ": [
        "2.5"
      ],
      " facility ": [],
      " cuisines ": [
        "North Indian",
        "Chinese"
      ],
      " cost_for_two ": "1,000",
      " hour ": "12noon \u2013 12midnight (Mon-Sun)",
      " featured ": [],
      " discount ": [
        "no discount"
      ]
    }
  },
  {
    "Dawat The Live Kitchen": {
      " url ": "https://www.zomato.com/ncr/dawat-the-live-kitchen-sector-37-gurgaon",
      " location ": " SCO-77, Sector-10 A, Near Sector 37, Gurgaon",
      " rating ": [
        "3.6",
        "3.4"
      ],
      " facility ": [],
      " cuisines ": [
        "Mughlai",
        "Chinese",
        "North Indian"
      ],
      " cost_for_two ": "600",
      " hour ": "11am \u2013 11pm (Mon-Sun)",
      " featured ": [],
      " discount ": [
        "10% off on all orders above \u20b999"
      ]
    },
    "Aakib Chickan Point": {
      " url ": "https://www.zomato.com/ncr/aakib-chickan-point-south-extension-2-new-delhi",
      " location ": " 436, Leela Ram Market, Masjid Moth, South Extension 2, New Delhi",
      " rating ": [
        "3.2",
        "4.1"
      ],
      " facility ": [],
      " cuisines ": [
        "Biryani"
      ],
      " cost_for_two ": "250",
      " hour ": "11am \u2013 8pm (Mon-Sun)",
      " featured ": [],
      " discount ": [
        "no discount"
      ]
    },
    "Order Cake Online": {
      " url ": "https://www.zomato.com/ncr/order-cake-online-2-palam-new-delhi",
      " location ": " WZ 507A, Opposite Dwarka Flyover, Pillar 59, Palam Colony, Palam, New Delhi",
      " rating ": [
        "3.3"
      ],
      " facility ": [],
      " cuisines ": [
        "Bakery",
        "Desserts"
      ],
      " cost_for_two ": "300",
      " hour ": "10am \u2013 10pm (Mon-Sun)",
      " featured ": [],
      " discount ": [
        "15% off on all orders above \u20b9300"
      ]
    },
    "OM Food Plaza": {
      " url ": "https://www.zomato.com/ncr/om-food-plaza-zeta-1-greater-noida",
      " location ": " Shop A 17, AVJ Hights, Zeta 1, Greater Noida",
      " rating ": [
        "3.2",
        "3.3"
      ],
      " facility ": [],
      " cuisines ": [
        "North Indian",
        "Chinese"
      ],
      " cost_for_two ": "250",
      " hour ": "10am \u2013 10pm (Mon-Sun)",
      " featured ": [],
      " discount ": [
        "no discount"
      ]
    },
    "Rahul Food Court": {
      " url ": "https://www.zomato.com/ncr/rahul-food-court-sector-37-gurgaon",
      " location ": " Shop 208/18, Khandsa Road, Opposite DAV School, Near Sector 37, Gurgaon",
      " rating ": [
        "3.1"
      ],
      " facility ": [],
      " cuisines ": [
        "South Indian",
        "North Indian"
      ],
      " cost_for_two ": "200",
      " hour ": "11am \u2013 11pm (Mon-Sun)",
      " featured ": [],
      " discount ": [
        "no discount"
      ]
    },
    "Samrat The Cake Shoppe": {
      " url ": "https://www.zomato.com/ncr/samrat-the-cake-shoppe-old-railway-road-gurgaon",
      " location ": " Sohna Chowk, Old Railway Road, Gurgaon",
      " rating ": [
        "2.7"
      ],
      " facility ": [],
      " cuisines ": [
        "Bakery",
        "Mithai",
        "Desserts",
        "Street Food",
        "Fast Food"
      ],
      " cost_for_two ": "300",
      " hour ": "8am \u2013 10:30pm (Mon-Sun)",
      " featured ": [],
      " discount ": [
        "no discount"
      ]
    },
    "Sanjay Chicken Corner": {
      " url ": "https://www.zomato.com/ncr/sanjay-chicken-corner-nangloi-new-delhi",
      " location ": " 325, Plot C-26A, Khasra 6472, Chandan Vihar, Near Aata Chakki, Nihal Vihar, Phase 2, Nangloi, New Delhi",
      " rating ": [
        "3.4",
        "3.2"
      ],
      " facility ": [],
      " cuisines ": [
        "Fast Food"
      ],
      " cost_for_two ": "400",
      " hour ": "4pm \u2013 12midnight (Mon-Sun)",
      " featured ": [],
      " discount ": [
        "no discount"
      ]
    },
    "The Friends' Republic": {
      " url ": "https://www.zomato.com/ncr/the-friends-republic-dlf-phase-5-gurgaon",
      " location ": " Opposite Paras Hospital, St. Thomas Marg, Sector 53, DLF Phase 5, Gurgaon",
      " rating ": [
        "2.5"
      ],
      " facility ": [],
      " cuisines ": [
        "North Indian",
        "Chinese"
      ],
      " cost_for_two ": "1,000",
      " hour ": "12noon \u2013 12midnight (Mon-Sun)",
      " featured ": [],
      " discount ": [
        "no discount"
      ]
    },
    "Paranthe Wali Gali": {
      " url ": "https://www.zomato.com/ncr/paranthe-wali-gali-rajouri-garden-new-delhi",
      " location ": " City Square Mall, FC 10, 4th Floor, Rajouri Garden, New Delhi",
      " rating ": [
        "3.1",
        "3.1"
      ],
      " facility ": [],
      " cuisines ": [
        "North Indian",
        "Street Food"
      ],
      " cost_for_two ": "500",
      " hour ": "11am \u2013 11pm (Mon-Sun)",
      " featured ": [],
      " discount ": [
        "no discount"
      ]
    }
  },
  {
    "Dawat The Live Kitchen": {
      " url ": "https://www.zomato.com/ncr/dawat-the-live-kitchen-sector-37-gurgaon",
      " location ": " SCO-77, Sector-10 A, Near Sector 37, Gurgaon",
      " rating ": [
        "3.6",
        "3.4"
      ],
      " facility ": [],
      " cuisines ": [
        "Mughlai",
        "Chinese",
        "North Indian"
      ],
      " cost_for_two ": "600",
      " hour ": "11am \u2013 11pm (Mon-Sun)",
      " featured ": [],
      " discount ": [
        "10% off on all orders above \u20b999"
      ]
    },
    "Aakib Chickan Point": {
      " url ": "https://www.zomato.com/ncr/aakib-chickan-point-south-extension-2-new-delhi",
      " location ": " 436, Leela Ram Market, Masjid Moth, South Extension 2, New Delhi",
      " rating ": [
        "3.2",
        "4.1"
      ],
      " facility ": [],
      " cuisines ": [
        "Biryani"
      ],
      " cost_for_two ": "250",
      " hour ": "11am \u2013 8pm (Mon-Sun)",
      " featured ": [],
      " discount ": [
        "no discount"
      ]
    },
    "Order Cake Online": {
      " url ": "https://www.zomato.com/ncr/order-cake-online-2-palam-new-delhi",
      " location ": " WZ 507A, Opposite Dwarka Flyover, Pillar 59, Palam Colony, Palam, New Delhi",
      " rating ": [
        "3.3"
      ],
      " facility ": [],
      " cuisines ": [
        "Bakery",
        "Desserts"
      ],
      " cost_for_two ": "300",
      " hour ": "10am \u2013 10pm (Mon-Sun)",
      " featured ": [],
      " discount ": [
        "15% off on all orders above \u20b9300"
      ]
    },
    "OM Food Plaza": {
      " url ": "https://www.zomato.com/ncr/om-food-plaza-zeta-1-greater-noida",
      " location ": " Shop A 17, AVJ Hights, Zeta 1, Greater Noida",
      " rating ": [
        "3.2",
        "3.3"
      ],
      " facility ": [],
      " cuisines ": [
        "North Indian",
        "Chinese"
      ],
      " cost_for_two ": "250",
      " hour ": "10am \u2013 10pm (Mon-Sun)",
      " featured ": [],
      " discount ": [
        "no discount"
      ]
    },
    "Rahul Food Court": {
      " url ": "https://www.zomato.com/ncr/rahul-food-court-sector-37-gurgaon",
      " location ": " Shop 208/18, Khandsa Road, Opposite DAV School, Near Sector 37, Gurgaon",
      " rating ": [
        "3.1"
      ],
      " facility ": [],
      " cuisines ": [
        "South Indian",
        "North Indian"
      ],
      " cost_for_two ": "200",
      " hour ": "11am \u2013 11pm (Mon-Sun)",
      " featured ": [],
      " discount ": [
        "no discount"
      ]
    },
    "Samrat The Cake Shoppe": {
      " url ": "https://www.zomato.com/ncr/samrat-the-cake-shoppe-old-railway-road-gurgaon",
      " location ": " Sohna Chowk, Old Railway Road, Gurgaon",
      " rating ": [
        "2.7"
      ],
      " facility ": [],
      " cuisines ": [
        "Bakery",
        "Mithai",
        "Desserts",
        "Street Food",
        "Fast Food"
      ],
      " cost_for_two ": "300",
      " hour ": "8am \u2013 10:30pm (Mon-Sun)",
      " featured ": [],
      " discount ": [
        "no discount"
      ]
    },
    "Sanjay Chicken Corner": {
      " url ": "https://www.zomato.com/ncr/sanjay-chicken-corner-nangloi-new-delhi",
      " location ": " 325, Plot C-26A, Khasra 6472, Chandan Vihar, Near Aata Chakki, Nihal Vihar, Phase 2, Nangloi, New Delhi",
      " rating ": [
        "3.4",
        "3.2"
      ],
      " facility ": [],
      " cuisines ": [
        "Fast Food"
      ],
      " cost_for_two ": "400",
      " hour ": "4pm \u2013 12midnight (Mon-Sun)",
      " featured ": [],
      " discount ": [
        "no discount"
      ]
    },
    "The Friends' Republic": {
      " url ": "https://www.zomato.com/ncr/the-friends-republic-dlf-phase-5-gurgaon",
      " location ": " Opposite Paras Hospital, St. Thomas Marg, Sector 53, DLF Phase 5, Gurgaon",
      " rating ": [
        "2.5"
      ],
      " facility ": [],
      " cuisines ": [
        "North Indian",
        "Chinese"
      ],
      " cost_for_two ": "1,000",
      " hour ": "12noon \u2013 12midnight (Mon-Sun)",
      " featured ": [],
      " discount ": [
        "no discount"
      ]
    },
    "Paranthe Wali Gali": {
      " url ": "https://www.zomato.com/ncr/paranthe-wali-gali-rajouri-garden-new-delhi",
      " location ": " City Square Mall, FC 10, 4th Floor, Rajouri Garden, New Delhi",
      " rating ": [
        "3.1",
        "3.1"
      ],
      " facility ": [],
      " cuisines ": [
        "North Indian",
        "Street Food"
      ],
      " cost_for_two ": "500",
      " hour ": "11am \u2013 11pm (Mon-Sun)",
      " featured ": [],
      " discount ": [
        "no discount"
      ]
    },
    "Tandoori Nation": {
      " url ": "https://www.zomato.com/ncr/tandoori-nation-1-sohna-road-gurgaon",
      " location ": " Shop 95, Sindhi Namkeen Vyapar Kendra, Sector 43, Sohna Road, Gurgaon",
      " rating ": [
        "3.5",
        "3.3"
      ],
      " facility ": [],
      " cuisines ": [
        "North Indian",
        "Rolls",
        "Momos"
      ],
      " cost_for_two ": "550",
      " hour ": "12noon \u2013 11pm (Mon-Sun)",
      " featured ": [],
      " discount ": [
        "no discount"
      ]
    }
  },
  {
    "Dawat The Live Kitchen": {
      " url ": "https://www.zomato.com/ncr/dawat-the-live-kitchen-sector-37-gurgaon",
      " location ": " SCO-77, Sector-10 A, Near Sector 37, Gurgaon",
      " rating ": [
        "3.6",
        "3.4"
      ],
      " facility ": [],
      " cuisines ": [
        "Mughlai",
        "Chinese",
        "North Indian"
      ],
      " cost_for_two ": "600",
      " hour ": "11am \u2013 11pm (Mon-Sun)",
      " featured ": [],
      " discount ": [
        "10% off on all orders above \u20b999"
      ]
    },
    "Aakib Chickan Point": {
      " url ": "https://www.zomato.com/ncr/aakib-chickan-point-south-extension-2-new-delhi",
      " location ": " 436, Leela Ram Market, Masjid Moth, South Extension 2, New Delhi",
      " rating ": [
        "3.2",
        "4.1"
      ],
      " facility ": [],
      " cuisines ": [
        "Biryani"
      ],
      " cost_for_two ": "250",
      " hour ": "11am \u2013 8pm (Mon-Sun)",
      " featured ": [],
      " discount ": [
        "no discount"
      ]
    },
    "Order Cake Online": {
      " url ": "https://www.zomato.com/ncr/order-cake-online-2-palam-new-delhi",
      " location ": " WZ 507A, Opposite Dwarka Flyover, Pillar 59, Palam Colony, Palam, New Delhi",
      " rating ": [
        "3.3"
      ],
      " facility ": [],
      " cuisines ": [
        "Bakery",
        "Desserts"
      ],
      " cost_for_two ": "300",
      " hour ": "10am \u2013 10pm (Mon-Sun)",
      " featured ": [],
      " discount ": [
        "15% off on all orders above \u20b9300"
      ]
    },
    "OM Food Plaza": {
      " url ": "https://www.zomato.com/ncr/om-food-plaza-zeta-1-greater-noida",
      " location ": " Shop A 17, AVJ Hights, Zeta 1, Greater Noida",
      " rating ": [
        "3.2",
        "3.3"
      ],
      " facility ": [],
      " cuisines ": [
        "North Indian",
        "Chinese"
      ],
      " cost_for_two ": "250",
      " hour ": "10am \u2013 10pm (Mon-Sun)",
      " featured ": [],
      " discount ": [
        "no discount"
      ]
    },
    "Rahul Food Court": {
      " url ": "https://www.zomato.com/ncr/rahul-food-court-sector-37-gurgaon",
      " location ": " Shop 208/18, Khandsa Road, Opposite DAV School, Near Sector 37, Gurgaon",
      " rating ": [
        "3.1"
      ],
      " facility ": [],
      " cuisines ": [
        "South Indian",
        "North Indian"
      ],
      " cost_for_two ": "200",
      " hour ": "11am \u2013 11pm (Mon-Sun)",
      " featured ": [],
      " discount ": [
        "no discount"
      ]
    },
    "Samrat The Cake Shoppe": {
      " url ": "https://www.zomato.com/ncr/samrat-the-cake-shoppe-old-railway-road-gurgaon",
      " location ": " Sohna Chowk, Old Railway Road, Gurgaon",
      " rating ": [
        "2.7"
      ],
      " facility ": [],
      " cuisines ": [
        "Bakery",
        "Mithai",
        "Desserts",
        "Street Food",
        "Fast Food"
      ],
      " cost_for_two ": "300",
      " hour ": "8am \u2013 10:30pm (Mon-Sun)",
      " featured ": [],
      " discount ": [
        "no discount"
      ]
    },
    "Sanjay Chicken Corner": {
      " url ": "https://www.zomato.com/ncr/sanjay-chicken-corner-nangloi-new-delhi",
      " location ": " 325, Plot C-26A, Khasra 6472, Chandan Vihar, Near Aata Chakki, Nihal Vihar, Phase 2, Nangloi, New Delhi",
      " rating ": [
        "3.4",
        "3.2"
      ],
      " facility ": [],
      " cuisines ": [
        "Fast Food"
      ],
      " cost_for_two ": "400",
      " hour ": "4pm \u2013 12midnight (Mon-Sun)",
      " featured ": [],
      " discount ": [
        "no discount"
      ]
    },
    "The Friends' Republic": {
      " url ": "https://www.zomato.com/ncr/the-friends-republic-dlf-phase-5-gurgaon",
      " location ": " Opposite Paras Hospital, St. Thomas Marg, Sector 53, DLF Phase 5, Gurgaon",
      " rating ": [
        "2.5"
      ],
      " facility ": [],
      " cuisines ": [
        "North Indian",
        "Chinese"
      ],
      " cost_for_two ": "1,000",
      " hour ": "12noon \u2013 12midnight (Mon-Sun)",
      " featured ": [],
      " discount ": [
        "no discount"
      ]
    },
    "Paranthe Wali Gali": {
      " url ": "https://www.zomato.com/ncr/paranthe-wali-gali-rajouri-garden-new-delhi",
      " location ": " City Square Mall, FC 10, 4th Floor, Rajouri Garden, New Delhi",
      " rating ": [
        "3.1",
        "3.1"
      ],
      " facility ": [],
      " cuisines ": [
        "North Indian",
        "Street Food"
      ],
      " cost_for_two ": "500",
      " hour ": "11am \u2013 11pm (Mon-Sun)",
      " featured ": [],
      " discount ": [
        "no discount"
      ]
    },
    "Tandoori Nation": {
      " url ": "https://www.zomato.com/ncr/tandoori-nation-1-sohna-road-gurgaon",
      " location ": " Shop 95, Sindhi Namkeen Vyapar Kendra, Sector 43, Sohna Road, Gurgaon",
      " rating ": [
        "3.5",
        "3.3"
      ],
      " facility ": [],
      " cuisines ": [
        "North Indian",
        "Rolls",
        "Momos"
      ],
      " cost_for_two ": "550",
      " hour ": "12noon \u2013 11pm (Mon-Sun)",
      " featured ": [],
      " discount ": [
        "no discount"
      ]
    },
    "Deepak Fast Food": {
      " url ": "https://www.zomato.com/ncr/deepak-fast-food-1-vijay-nagar-new-delhi",
      " location ": " B Block, Vijay Nagar, New Delhi",
      " rating ": [
        "3.5"
      ],
      " facility ": [],
      " cuisines ": [
        "Chinese"
      ],
      " cost_for_two ": "350",
      " hour ": "11am \u2013 10:30pm (Mon-Sun)",
      " featured ": [],
      " discount ": [
        "no discount"
      ]
    }
  },
  {
    "Dawat The Live Kitchen": {
      " url ": "https://www.zomato.com/ncr/dawat-the-live-kitchen-sector-37-gurgaon",
      " location ": " SCO-77, Sector-10 A, Near Sector 37, Gurgaon",
      " rating ": [
        "3.6",
        "3.4"
      ],
      " facility ": [],
      " cuisines ": [
        "Mughlai",
        "Chinese",
        "North Indian"
      ],
      " cost_for_two ": "600",
      " hour ": "11am \u2013 11pm (Mon-Sun)",
      " featured ": [],
      " discount ": [
        "10% off on all orders above \u20b999"
      ]
    },
    "Aakib Chickan Point": {
      " url ": "https://www.zomato.com/ncr/aakib-chickan-point-south-extension-2-new-delhi",
      " location ": " 436, Leela Ram Market, Masjid Moth, South Extension 2, New Delhi",
      " rating ": [
        "3.2",
        "4.1"
      ],
      " facility ": [],
      " cuisines ": [
        "Biryani"
      ],
      " cost_for_two ": "250",
      " hour ": "11am \u2013 8pm (Mon-Sun)",
      " featured ": [],
      " discount ": [
        "no discount"
      ]
    },
    "Order Cake Online": {
      " url ": "https://www.zomato.com/ncr/order-cake-online-2-palam-new-delhi",
      " location ": " WZ 507A, Opposite Dwarka Flyover, Pillar 59, Palam Colony, Palam, New Delhi",
      " rating ": [
        "3.3"
      ],
      " facility ": [],
      " cuisines ": [
        "Bakery",
        "Desserts"
      ],
      " cost_for_two ": "300",
      " hour ": "10am \u2013 10pm (Mon-Sun)",
      " featured ": [],
      " discount ": [
        "15% off on all orders above \u20b9300"
      ]
    },
    "OM Food Plaza": {
      " url ": "https://www.zomato.com/ncr/om-food-plaza-zeta-1-greater-noida",
      " location ": " Shop A 17, AVJ Hights, Zeta 1, Greater Noida",
      " rating ": [
        "3.2",
        "3.3"
      ],
      " facility ": [],
      " cuisines ": [
        "North Indian",
        "Chinese"
      ],
      " cost_for_two ": "250",
      " hour ": "10am \u2013 10pm (Mon-Sun)",
      " featured ": [],
      " discount ": [
        "no discount"
      ]
    },
    "Rahul Food Court": {
      " url ": "https://www.zomato.com/ncr/rahul-food-court-sector-37-gurgaon",
      " location ": " Shop 208/18, Khandsa Road, Opposite DAV School, Near Sector 37, Gurgaon",
      " rating ": [
        "3.1"
      ],
      " facility ": [],
      " cuisines ": [
        "South Indian",
        "North Indian"
      ],
      " cost_for_two ": "200",
      " hour ": "11am \u2013 11pm (Mon-Sun)",
      " featured ": [],
      " discount ": [
        "no discount"
      ]
    },
    "Samrat The Cake Shoppe": {
      " url ": "https://www.zomato.com/ncr/samrat-the-cake-shoppe-old-railway-road-gurgaon",
      " location ": " Sohna Chowk, Old Railway Road, Gurgaon",
      " rating ": [
        "2.7"
      ],
      " facility ": [],
      " cuisines ": [
        "Bakery",
        "Mithai",
        "Desserts",
        "Street Food",
        "Fast Food"
      ],
      " cost_for_two ": "300",
      " hour ": "8am \u2013 10:30pm (Mon-Sun)",
      " featured ": [],
      " discount ": [
        "no discount"
      ]
    },
    "Sanjay Chicken Corner": {
      " url ": "https://www.zomato.com/ncr/sanjay-chicken-corner-nangloi-new-delhi",
      " location ": " 325, Plot C-26A, Khasra 6472, Chandan Vihar, Near Aata Chakki, Nihal Vihar, Phase 2, Nangloi, New Delhi",
      " rating ": [
        "3.4",
        "3.2"
      ],
      " facility ": [],
      " cuisines ": [
        "Fast Food"
      ],
      " cost_for_two ": "400",
      " hour ": "4pm \u2013 12midnight (Mon-Sun)",
      " featured ": [],
      " discount ": [
        "no discount"
      ]
    },
    "The Friends' Republic": {
      " url ": "https://www.zomato.com/ncr/the-friends-republic-dlf-phase-5-gurgaon",
      " location ": " Opposite Paras Hospital, St. Thomas Marg, Sector 53, DLF Phase 5, Gurgaon",
      " rating ": [
        "2.5"
      ],
      " facility ": [],
      " cuisines ": [
        "North Indian",
        "Chinese"
      ],
      " cost_for_two ": "1,000",
      " hour ": "12noon \u2013 12midnight (Mon-Sun)",
      " featured ": [],
      " discount ": [
        "no discount"
      ]
    },
    "Paranthe Wali Gali": {
      " url ": "https://www.zomato.com/ncr/paranthe-wali-gali-rajouri-garden-new-delhi",
      " location ": " City Square Mall, FC 10, 4th Floor, Rajouri Garden, New Delhi",
      " rating ": [
        "3.1",
        "3.1"
      ],
      " facility ": [],
      " cuisines ": [
        "North Indian",
        "Street Food"
      ],
      " cost_for_two ": "500",
      " hour ": "11am \u2013 11pm (Mon-Sun)",
      " featured ": [],
      " discount ": [
        "no discount"
      ]
    },
    "Tandoori Nation": {
      " url ": "https://www.zomato.com/ncr/tandoori-nation-1-sohna-road-gurgaon",
      " location ": " Shop 95, Sindhi Namkeen Vyapar Kendra, Sector 43, Sohna Road, Gurgaon",
      " rating ": [
        "3.5",
        "3.3"
      ],
      " facility ": [],
      " cuisines ": [
        "North Indian",
        "Rolls",
        "Momos"
      ],
      " cost_for_two ": "550",
      " hour ": "12noon \u2013 11pm (Mon-Sun)",
      " featured ": [],
      " discount ": [
        "no discount"
      ]
    },
    "Deepak Fast Food": {
      " url ": "https://www.zomato.com/ncr/deepak-fast-food-1-vijay-nagar-new-delhi",
      " location ": " B Block, Vijay Nagar, New Delhi",
      " rating ": [
        "3.5"
      ],
      " facility ": [],
      " cuisines ": [
        "Chinese"
      ],
      " cost_for_two ": "350",
      " hour ": "11am \u2013 10:30pm (Mon-Sun)",
      " featured ": [],
      " discount ": [
        "no discount"
      ]
    },
    "Loaves & Kisses": {
      " url ": "https://www.zomato.com/ncr/loaves-kisses-south-city-gurgaon",
      " location ": " Club Patio, E Block, Near NH 8, South City 1, Gurgaon",
      " rating ": [
        "3.1"
      ],
      " facility ": [],
      " cuisines ": [
        "Bakery",
        "Desserts",
        "Beverages"
      ],
      " cost_for_two ": "250",
      " hour ": "8am \u2013 10:30pm (Mon-Sun)",
      " featured ": [],
      " discount ": [
        "no discount"
      ]
    }
  },
  {
    "Dawat The Live Kitchen": {
      " url ": "https://www.zomato.com/ncr/dawat-the-live-kitchen-sector-37-gurgaon",
      " location ": " SCO-77, Sector-10 A, Near Sector 37, Gurgaon",
      " rating ": [
        "3.6",
        "3.4"
      ],
      " facility ": [],
      " cuisines ": [
        "Mughlai",
        "Chinese",
        "North Indian"
      ],
      " cost_for_two ": "600",
      " hour ": "11am \u2013 11pm (Mon-Sun)",
      " featured ": [],
      " discount ": [
        "10% off on all orders above \u20b999"
      ]
    },
    "Aakib Chickan Point": {
      " url ": "https://www.zomato.com/ncr/aakib-chickan-point-south-extension-2-new-delhi",
      " location ": " 436, Leela Ram Market, Masjid Moth, South Extension 2, New Delhi",
      " rating ": [
        "3.2",
        "4.1"
      ],
      " facility ": [],
      " cuisines ": [
        "Biryani"
      ],
      " cost_for_two ": "250",
      " hour ": "11am \u2013 8pm (Mon-Sun)",
      " featured ": [],
      " discount ": [
        "no discount"
      ]
    },
    "Order Cake Online": {
      " url ": "https://www.zomato.com/ncr/order-cake-online-2-palam-new-delhi",
      " location ": " WZ 507A, Opposite Dwarka Flyover, Pillar 59, Palam Colony, Palam, New Delhi",
      " rating ": [
        "3.3"
      ],
      " facility ": [],
      " cuisines ": [
        "Bakery",
        "Desserts"
      ],
      " cost_for_two ": "300",
      " hour ": "10am \u2013 10pm (Mon-Sun)",
      " featured ": [],
      " discount ": [
        "15% off on all orders above \u20b9300"
      ]
    },
    "OM Food Plaza": {
      " url ": "https://www.zomato.com/ncr/om-food-plaza-zeta-1-greater-noida",
      " location ": " Shop A 17, AVJ Hights, Zeta 1, Greater Noida",
      " rating ": [
        "3.2",
        "3.3"
      ],
      " facility ": [],
      " cuisines ": [
        "North Indian",
        "Chinese"
      ],
      " cost_for_two ": "250",
      " hour ": "10am \u2013 10pm (Mon-Sun)",
      " featured ": [],
      " discount ": [
        "no discount"
      ]
    },
    "Rahul Food Court": {
      " url ": "https://www.zomato.com/ncr/rahul-food-court-sector-37-gurgaon",
      " location ": " Shop 208/18, Khandsa Road, Opposite DAV School, Near Sector 37, Gurgaon",
      " rating ": [
        "3.1"
      ],
      " facility ": [],
      " cuisines ": [
        "South Indian",
        "North Indian"
      ],
      " cost_for_two ": "200",
      " hour ": "11am \u2013 11pm (Mon-Sun)",
      " featured ": [],
      " discount ": [
        "no discount"
      ]
    },
    "Samrat The Cake Shoppe": {
      " url ": "https://www.zomato.com/ncr/samrat-the-cake-shoppe-old-railway-road-gurgaon",
      " location ": " Sohna Chowk, Old Railway Road, Gurgaon",
      " rating ": [
        "2.7"
      ],
      " facility ": [],
      " cuisines ": [
        "Bakery",
        "Mithai",
        "Desserts",
        "Street Food",
        "Fast Food"
      ],
      " cost_for_two ": "300",
      " hour ": "8am \u2013 10:30pm (Mon-Sun)",
      " featured ": [],
      " discount ": [
        "no discount"
      ]
    },
    "Sanjay Chicken Corner": {
      " url ": "https://www.zomato.com/ncr/sanjay-chicken-corner-nangloi-new-delhi",
      " location ": " 325, Plot C-26A, Khasra 6472, Chandan Vihar, Near Aata Chakki, Nihal Vihar, Phase 2, Nangloi, New Delhi",
      " rating ": [
        "3.4",
        "3.2"
      ],
      " facility ": [],
      " cuisines ": [
        "Fast Food"
      ],
      " cost_for_two ": "400",
      " hour ": "4pm \u2013 12midnight (Mon-Sun)",
      " featured ": [],
      " discount ": [
        "no discount"
      ]
    },
    "The Friends' Republic": {
      " url ": "https://www.zomato.com/ncr/the-friends-republic-dlf-phase-5-gurgaon",
      " location ": " Opposite Paras Hospital, St. Thomas Marg, Sector 53, DLF Phase 5, Gurgaon",
      " rating ": [
        "2.5"
      ],
      " facility ": [],
      " cuisines ": [
        "North Indian",
        "Chinese"
      ],
      " cost_for_two ": "1,000",
      " hour ": "12noon \u2013 12midnight (Mon-Sun)",
      " featured ": [],
      " discount ": [
        "no discount"
      ]
    },
    "Paranthe Wali Gali": {
      " url ": "https://www.zomato.com/ncr/paranthe-wali-gali-rajouri-garden-new-delhi",
      " location ": " City Square Mall, FC 10, 4th Floor, Rajouri Garden, New Delhi",
      " rating ": [
        "3.1",
        "3.1"
      ],
      " facility ": [],
      " cuisines ": [
        "North Indian",
        "Street Food"
      ],
      " cost_for_two ": "500",
      " hour ": "11am \u2013 11pm (Mon-Sun)",
      " featured ": [],
      " discount ": [
        "no discount"
      ]
    },
    "Tandoori Nation": {
      " url ": "https://www.zomato.com/ncr/tandoori-nation-1-sohna-road-gurgaon",
      " location ": " Shop 95, Sindhi Namkeen Vyapar Kendra, Sector 43, Sohna Road, Gurgaon",
      " rating ": [
        "3.5",
        "3.3"
      ],
      " facility ": [],
      " cuisines ": [
        "North Indian",
        "Rolls",
        "Momos"
      ],
      " cost_for_two ": "550",
      " hour ": "12noon \u2013 11pm (Mon-Sun)",
      " featured ": [],
      " discount ": [
        "no discount"
      ]
    },
    "Deepak Fast Food": {
      " url ": "https://www.zomato.com/ncr/deepak-fast-food-1-vijay-nagar-new-delhi",
      " location ": " B Block, Vijay Nagar, New Delhi",
      " rating ": [
        "3.5"
      ],
      " facility ": [],
      " cuisines ": [
        "Chinese"
      ],
      " cost_for_two ": "350",
      " hour ": "11am \u2013 10:30pm (Mon-Sun)",
      " featured ": [],
      " discount ": [
        "no discount"
      ]
    },
    "Loaves & Kisses": {
      " url ": "https://www.zomato.com/ncr/loaves-kisses-south-city-gurgaon",
      " location ": " Club Patio, E Block, Near NH 8, South City 1, Gurgaon",
      " rating ": [
        "3.1"
      ],
      " facility ": [],
      " cuisines ": [
        "Bakery",
        "Desserts",
        "Beverages"
      ],
      " cost_for_two ": "250",
      " hour ": "8am \u2013 10:30pm (Mon-Sun)",
      " featured ": [],
      " discount ": [
        "no discount"
      ]
    },
    "Dellhi 999": {
      " url ": "https://www.zomato.com/ncr/dellhi-999-badarpur-border-faridabad",
      " location ": " Aggarwal Dharamshala Road, Lakhpat Colony, Mithapur, Badarpur Border, Faridabad",
      " rating ": [
        "2.9"
      ],
      " facility ": [],
      " cuisines ": [
        "Pizza",
        "Fast Food"
      ],
      " cost_for_two ": "300",
      " hour ": "10am \u2013 10pm (Mon-Sun)",
      " featured ": [],
      " discount ": [
        "no discount"
      ]
    }
  },
  {
    "Dawat The Live Kitchen": {
      " url ": "https://www.zomato.com/ncr/dawat-the-live-kitchen-sector-37-gurgaon",
      " location ": " SCO-77, Sector-10 A, Near Sector 37, Gurgaon",
      " rating ": [
        "3.6",
        "3.4"
      ],
      " facility ": [],
      " cuisines ": [
        "Mughlai",
        "Chinese",
        "North Indian"
      ],
      " cost_for_two ": "600",
      " hour ": "11am \u2013 11pm (Mon-Sun)",
      " featured ": [],
      " discount ": [
        "10% off on all orders above \u20b999"
      ]
    },
    "Aakib Chickan Point": {
      " url ": "https://www.zomato.com/ncr/aakib-chickan-point-south-extension-2-new-delhi",
      " location ": " 436, Leela Ram Market, Masjid Moth, South Extension 2, New Delhi",
      " rating ": [
        "3.2",
        "4.1"
      ],
      " facility ": [],
      " cuisines ": [
        "Biryani"
      ],
      " cost_for_two ": "250",
      " hour ": "11am \u2013 8pm (Mon-Sun)",
      " featured ": [],
      " discount ": [
        "no discount"
      ]
    },
    "Order Cake Online": {
      " url ": "https://www.zomato.com/ncr/order-cake-online-2-palam-new-delhi",
      " location ": " WZ 507A, Opposite Dwarka Flyover, Pillar 59, Palam Colony, Palam, New Delhi",
      " rating ": [
        "3.3"
      ],
      " facility ": [],
      " cuisines ": [
        "Bakery",
        "Desserts"
      ],
      " cost_for_two ": "300",
      " hour ": "10am \u2013 10pm (Mon-Sun)",
      " featured ": [],
      " discount ": [
        "15% off on all orders above \u20b9300"
      ]
    },
    "OM Food Plaza": {
      " url ": "https://www.zomato.com/ncr/om-food-plaza-zeta-1-greater-noida",
      " location ": " Shop A 17, AVJ Hights, Zeta 1, Greater Noida",
      " rating ": [
        "3.2",
        "3.3"
      ],
      " facility ": [],
      " cuisines ": [
        "North Indian",
        "Chinese"
      ],
      " cost_for_two ": "250",
      " hour ": "10am \u2013 10pm (Mon-Sun)",
      " featured ": [],
      " discount ": [
        "no discount"
      ]
    },
    "Rahul Food Court": {
      " url ": "https://www.zomato.com/ncr/rahul-food-court-sector-37-gurgaon",
      " location ": " Shop 208/18, Khandsa Road, Opposite DAV School, Near Sector 37, Gurgaon",
      " rating ": [
        "3.1"
      ],
      " facility ": [],
      " cuisines ": [
        "South Indian",
        "North Indian"
      ],
      " cost_for_two ": "200",
      " hour ": "11am \u2013 11pm (Mon-Sun)",
      " featured ": [],
      " discount ": [
        "no discount"
      ]
    },
    "Samrat The Cake Shoppe": {
      " url ": "https://www.zomato.com/ncr/samrat-the-cake-shoppe-old-railway-road-gurgaon",
      " location ": " Sohna Chowk, Old Railway Road, Gurgaon",
      " rating ": [
        "2.7"
      ],
      " facility ": [],
      " cuisines ": [
        "Bakery",
        "Mithai",
        "Desserts",
        "Street Food",
        "Fast Food"
      ],
      " cost_for_two ": "300",
      " hour ": "8am \u2013 10:30pm (Mon-Sun)",
      " featured ": [],
      " discount ": [
        "no discount"
      ]
    },
    "Sanjay Chicken Corner": {
      " url ": "https://www.zomato.com/ncr/sanjay-chicken-corner-nangloi-new-delhi",
      " location ": " 325, Plot C-26A, Khasra 6472, Chandan Vihar, Near Aata Chakki, Nihal Vihar, Phase 2, Nangloi, New Delhi",
      " rating ": [
        "3.4",
        "3.2"
      ],
      " facility ": [],
      " cuisines ": [
        "Fast Food"
      ],
      " cost_for_two ": "400",
      " hour ": "4pm \u2013 12midnight (Mon-Sun)",
      " featured ": [],
      " discount ": [
        "no discount"
      ]
    },
    "The Friends' Republic": {
      " url ": "https://www.zomato.com/ncr/the-friends-republic-dlf-phase-5-gurgaon",
      " location ": " Opposite Paras Hospital, St. Thomas Marg, Sector 53, DLF Phase 5, Gurgaon",
      " rating ": [
        "2.5"
      ],
      " facility ": [],
      " cuisines ": [
        "North Indian",
        "Chinese"
      ],
      " cost_for_two ": "1,000",
      " hour ": "12noon \u2013 12midnight (Mon-Sun)",
      " featured ": [],
      " discount ": [
        "no discount"
      ]
    },
    "Paranthe Wali Gali": {
      " url ": "https://www.zomato.com/ncr/paranthe-wali-gali-rajouri-garden-new-delhi",
      " location ": " City Square Mall, FC 10, 4th Floor, Rajouri Garden, New Delhi",
      " rating ": [
        "3.1",
        "3.1"
      ],
      " facility ": [],
      " cuisines ": [
        "North Indian",
        "Street Food"
      ],
      " cost_for_two ": "500",
      " hour ": "11am \u2013 11pm (Mon-Sun)",
      " featured ": [],
      " discount ": [
        "no discount"
      ]
    },
    "Tandoori Nation": {
      " url ": "https://www.zomato.com/ncr/tandoori-nation-1-sohna-road-gurgaon",
      " location ": " Shop 95, Sindhi Namkeen Vyapar Kendra, Sector 43, Sohna Road, Gurgaon",
      " rating ": [
        "3.5",
        "3.3"
      ],
      " facility ": [],
      " cuisines ": [
        "North Indian",
        "Rolls",
        "Momos"
      ],
      " cost_for_two ": "550",
      " hour ": "12noon \u2013 11pm (Mon-Sun)",
      " featured ": [],
      " discount ": [
        "no discount"
      ]
    },
    "Deepak Fast Food": {
      " url ": "https://www.zomato.com/ncr/deepak-fast-food-1-vijay-nagar-new-delhi",
      " location ": " B Block, Vijay Nagar, New Delhi",
      " rating ": [
        "3.5"
      ],
      " facility ": [],
      " cuisines ": [
        "Chinese"
      ],
      " cost_for_two ": "350",
      " hour ": "11am \u2013 10:30pm (Mon-Sun)",
      " featured ": [],
      " discount ": [
        "no discount"
      ]
    },
    "Loaves & Kisses": {
      " url ": "https://www.zomato.com/ncr/loaves-kisses-south-city-gurgaon",
      " location ": " Club Patio, E Block, Near NH 8, South City 1, Gurgaon",
      " rating ": [
        "3.1"
      ],
      " facility ": [],
      " cuisines ": [
        "Bakery",
        "Desserts",
        "Beverages"
      ],
      " cost_for_two ": "250",
      " hour ": "8am \u2013 10:30pm (Mon-Sun)",
      " featured ": [],
      " discount ": [
        "no discount"
      ]
    },
    "Dellhi 999": {
      " url ": "https://www.zomato.com/ncr/dellhi-999-badarpur-border-faridabad",
      " location ": " Aggarwal Dharamshala Road, Lakhpat Colony, Mithapur, Badarpur Border, Faridabad",
      " rating ": [
        "2.9"
      ],
      " facility ": [],
      " cuisines ": [
        "Pizza",
        "Fast Food"
      ],
      " cost_for_two ": "300",
      " hour ": "10am \u2013 10pm (Mon-Sun)",
      " featured ": [],
      " discount ": [
        "no discount"
      ]
    },
    "Jija Saale Chole Bhature Wale": {
      " url ": "https://www.zomato.com/ncr/jija-saale-chole-bhature-wale-rohini-new-delhi",
      " location ": " C-5/278, Sector 6, Rohini, New Delhi",
      " rating ": [
        "3.1"
      ],
      " facility ": [],
      " cuisines ": [
        "Street Food"
      ],
      " cost_for_two ": "150",
      " hour ": "7:30am \u2013 8pm (Mon-Sun)",
      " featured ": [],
      " discount ": [
        "no discount"
      ]
    }
  },
  {
    "Dawat The Live Kitchen": {
      " url ": "https://www.zomato.com/ncr/dawat-the-live-kitchen-sector-37-gurgaon",
      " location ": " SCO-77, Sector-10 A, Near Sector 37, Gurgaon",
      " rating ": [
        "3.6",
        "3.4"
      ],
      " facility ": [],
      " cuisines ": [
        "Mughlai",
        "Chinese",
        "North Indian"
      ],
      " cost_for_two ": "600",
      " hour ": "11am \u2013 11pm (Mon-Sun)",
      " featured ": [],
      " discount ": [
        "10% off on all orders above \u20b999"
      ]
    },
    "Aakib Chickan Point": {
      " url ": "https://www.zomato.com/ncr/aakib-chickan-point-south-extension-2-new-delhi",
      " location ": " 436, Leela Ram Market, Masjid Moth, South Extension 2, New Delhi",
      " rating ": [
        "3.2",
        "4.1"
      ],
      " facility ": [],
      " cuisines ": [
        "Biryani"
      ],
      " cost_for_two ": "250",
      " hour ": "11am \u2013 8pm (Mon-Sun)",
      " featured ": [],
      " discount ": [
        "no discount"
      ]
    },
    "Order Cake Online": {
      " url ": "https://www.zomato.com/ncr/order-cake-online-2-palam-new-delhi",
      " location ": " WZ 507A, Opposite Dwarka Flyover, Pillar 59, Palam Colony, Palam, New Delhi",
      " rating ": [
        "3.3"
      ],
      " facility ": [],
      " cuisines ": [
        "Bakery",
        "Desserts"
      ],
      " cost_for_two ": "300",
      " hour ": "10am \u2013 10pm (Mon-Sun)",
      " featured ": [],
      " discount ": [
        "15% off on all orders above \u20b9300"
      ]
    },
    "OM Food Plaza": {
      " url ": "https://www.zomato.com/ncr/om-food-plaza-zeta-1-greater-noida",
      " location ": " Shop A 17, AVJ Hights, Zeta 1, Greater Noida",
      " rating ": [
        "3.2",
        "3.3"
      ],
      " facility ": [],
      " cuisines ": [
        "North Indian",
        "Chinese"
      ],
      " cost_for_two ": "250",
      " hour ": "10am \u2013 10pm (Mon-Sun)",
      " featured ": [],
      " discount ": [
        "no discount"
      ]
    },
    "Rahul Food Court": {
      " url ": "https://www.zomato.com/ncr/rahul-food-court-sector-37-gurgaon",
      " location ": " Shop 208/18, Khandsa Road, Opposite DAV School, Near Sector 37, Gurgaon",
      " rating ": [
        "3.1"
      ],
      " facility ": [],
      " cuisines ": [
        "South Indian",
        "North Indian"
      ],
      " cost_for_two ": "200",
      " hour ": "11am \u2013 11pm (Mon-Sun)",
      " featured ": [],
      " discount ": [
        "no discount"
      ]
    },
    "Samrat The Cake Shoppe": {
      " url ": "https://www.zomato.com/ncr/samrat-the-cake-shoppe-old-railway-road-gurgaon",
      " location ": " Sohna Chowk, Old Railway Road, Gurgaon",
      " rating ": [
        "2.7"
      ],
      " facility ": [],
      " cuisines ": [
        "Bakery",
        "Mithai",
        "Desserts",
        "Street Food",
        "Fast Food"
      ],
      " cost_for_two ": "300",
      " hour ": "8am \u2013 10:30pm (Mon-Sun)",
      " featured ": [],
      " discount ": [
        "no discount"
      ]
    },
    "Sanjay Chicken Corner": {
      " url ": "https://www.zomato.com/ncr/sanjay-chicken-corner-nangloi-new-delhi",
      " location ": " 325, Plot C-26A, Khasra 6472, Chandan Vihar, Near Aata Chakki, Nihal Vihar, Phase 2, Nangloi, New Delhi",
      " rating ": [
        "3.4",
        "3.2"
      ],
      " facility ": [],
      " cuisines ": [
        "Fast Food"
      ],
      " cost_for_two ": "400",
      " hour ": "4pm \u2013 12midnight (Mon-Sun)",
      " featured ": [],
      " discount ": [
        "no discount"
      ]
    },
    "The Friends' Republic": {
      " url ": "https://www.zomato.com/ncr/the-friends-republic-dlf-phase-5-gurgaon",
      " location ": " Opposite Paras Hospital, St. Thomas Marg, Sector 53, DLF Phase 5, Gurgaon",
      " rating ": [
        "2.5"
      ],
      " facility ": [],
      " cuisines ": [
        "North Indian",
        "Chinese"
      ],
      " cost_for_two ": "1,000",
      " hour ": "12noon \u2013 12midnight (Mon-Sun)",
      " featured ": [],
      " discount ": [
        "no discount"
      ]
    },
    "Paranthe Wali Gali": {
      " url ": "https://www.zomato.com/ncr/paranthe-wali-gali-rajouri-garden-new-delhi",
      " location ": " City Square Mall, FC 10, 4th Floor, Rajouri Garden, New Delhi",
      " rating ": [
        "3.1",
        "3.1"
      ],
      " facility ": [],
      " cuisines ": [
        "North Indian",
        "Street Food"
      ],
      " cost_for_two ": "500",
      " hour ": "11am \u2013 11pm (Mon-Sun)",
      " featured ": [],
      " discount ": [
        "no discount"
      ]
    },
    "Tandoori Nation": {
      " url ": "https://www.zomato.com/ncr/tandoori-nation-1-sohna-road-gurgaon",
      " location ": " Shop 95, Sindhi Namkeen Vyapar Kendra, Sector 43, Sohna Road, Gurgaon",
      " rating ": [
        "3.5",
        "3.3"
      ],
      " facility ": [],
      " cuisines ": [
        "North Indian",
        "Rolls",
        "Momos"
      ],
      " cost_for_two ": "550",
      " hour ": "12noon \u2013 11pm (Mon-Sun)",
      " featured ": [],
      " discount ": [
        "no discount"
      ]
    },
    "Deepak Fast Food": {
      " url ": "https://www.zomato.com/ncr/deepak-fast-food-1-vijay-nagar-new-delhi",
      " location ": " B Block, Vijay Nagar, New Delhi",
      " rating ": [
        "3.5"
      ],
      " facility ": [],
      " cuisines ": [
        "Chinese"
      ],
      " cost_for_two ": "350",
      " hour ": "11am \u2013 10:30pm (Mon-Sun)",
      " featured ": [],
      " discount ": [
        "no discount"
      ]
    },
    "Loaves & Kisses": {
      " url ": "https://www.zomato.com/ncr/loaves-kisses-south-city-gurgaon",
      " location ": " Club Patio, E Block, Near NH 8, South City 1, Gurgaon",
      " rating ": [
        "3.1"
      ],
      " facility ": [],
      " cuisines ": [
        "Bakery",
        "Desserts",
        "Beverages"
      ],
      " cost_for_two ": "250",
      " hour ": "8am \u2013 10:30pm (Mon-Sun)",
      " featured ": [],
      " discount ": [
        "no discount"
      ]
    },
    "Dellhi 999": {
      " url ": "https://www.zomato.com/ncr/dellhi-999-badarpur-border-faridabad",
      " location ": " Aggarwal Dharamshala Road, Lakhpat Colony, Mithapur, Badarpur Border, Faridabad",
      " rating ": [
        "2.9"
      ],
      " facility ": [],
      " cuisines ": [
        "Pizza",
        "Fast Food"
      ],
      " cost_for_two ": "300",
      " hour ": "10am \u2013 10pm (Mon-Sun)",
      " featured ": [],
      " discount ": [
        "no discount"
      ]
    },
    "Jija Saale Chole Bhature Wale": {
      " url ": "https://www.zomato.com/ncr/jija-saale-chole-bhature-wale-rohini-new-delhi",
      " location ": " C-5/278, Sector 6, Rohini, New Delhi",
      " rating ": [
        "3.1"
      ],
      " facility ": [],
      " cuisines ": [
        "Street Food"
      ],
      " cost_for_two ": "150",
      " hour ": "7:30am \u2013 8pm (Mon-Sun)",
      " featured ": [],
      " discount ": [
        "no discount"
      ]
    },
    "Pizza And Burger Hub": {
      " url ": "https://www.zomato.com/ncr/pizza-and-burger-hub-sector-125-noida",
      " location ": " Raipur Village, Near Amity University, Sector 126, Near Sector 125, Noida",
      " rating ": [
        "3.3",
        "3.7"
      ],
      " facility ": [],
      " cuisines ": [
        "Pizza",
        "Fast Food"
      ],
      " cost_for_two ": "500",
      " hour ": "11am \u2013 11pm (Mon-Sun)",
      " featured ": [],
      " discount ": [
        "40% off on all orders above \u20b9150"
      ]
    }
  }
]