[
  {
    "Mughal Garhi": {
      " url ": "https://www.zomato.com/ncr/mughal-garhi-sector-45-noida",
      " location ": " SDA-20, Near Shivalik Bank, Sector 45, Noida",
      " rating ": [
        "3.8"
      ],
      " facility ": [],
      " cuisines ": [
        "North Indian",
        "Chinese"
      ],
      " cost_for_two ": "500",
      " hour ": "6pm \u2013 4am (Mon-Sun)",
      " featured ": [],
      " discount ": [
        "10% off on all orders above \u20b9299"
      ]
    }
  },
  {
    "Mughal Garhi": {
      " url ": "https://www.zomato.com/ncr/mughal-garhi-sector-45-noida",
      " location ": " SDA-20, Near Shivalik Bank, Sector 45, Noida",
      " rating ": [
        "3.8"
      ],
      " facility ": [],
      " cuisines ": [
        "North Indian",
        "Chinese"
      ],
      " cost_for_two ": "500",
      " hour ": "6pm \u2013 4am (Mon-Sun)",
      " featured ": [],
      " discount ": [
        "10% off on all orders above \u20b9299"
      ]
    },
    "South Indian Anna Madras Cafe": {
      " url ": "https://www.zomato.com/ncr/south-indian-anna-madras-cafe-pandav-nagar-new-delhi",
      " location ": " 11, Pandav Nagar Complex, Ganesh Nagar, Pandav Nagar, New Delhi",
      " rating ": [
        "3.7",
        "3.8"
      ],
      " facility ": [],
      " cuisines ": [
        "South Indian"
      ],
      " cost_for_two ": "300",
      " hour ": "9am \u2013 10pm (Mon-Sun)",
      " featured ": [],
      " discount ": [
        "no discount"
      ]
    }
  },
  {
    "Mughal Garhi": {
      " url ": "https://www.zomato.com/ncr/mughal-garhi-sector-45-noida",
      " location ": " SDA-20, Near Shivalik Bank, Sector 45, Noida",
      " rating ": [
        "3.8"
      ],
      " facility ": [],
      " cuisines ": [
        "North Indian",
        "Chinese"
      ],
      " cost_for_two ": "500",
      " hour ": "6pm \u2013 4am (Mon-Sun)",
      " featured ": [],
      " discount ": [
        "10% off on all orders above \u20b9299"
      ]
    },
    "South Indian Anna Madras Cafe": {
      " url ": "https://www.zomato.com/ncr/south-indian-anna-madras-cafe-pandav-nagar-new-delhi",
      " location ": " 11, Pandav Nagar Complex, Ganesh Nagar, Pandav Nagar, New Delhi",
      " rating ": [
        "3.7",
        "3.8"
      ],
      " facility ": [],
      " cuisines ": [
        "South Indian"
      ],
      " cost_for_two ": "300",
      " hour ": "9am \u2013 10pm (Mon-Sun)",
      " featured ": [],
      " discount ": [
        "no discount"
      ]
    },
    "Food Point": {
      " url ": "https://www.zomato.com/ncr/food-point-2-rohini-new-delhi",
      " location ": " Delivery Only",
      " rating ": [],
      " facility ": [],
      " cuisines ": [
        "Chinese",
        "Fast Food"
      ],
      " cost_for_two ": "250",
      " hour ": "12:30pm \u2013 2am (Mon-Sun)",
      " featured ": [],
      " discount ": [
        "no discount"
      ]
    }
  },
  {
    "Mughal Garhi": {
      " url ": "https://www.zomato.com/ncr/mughal-garhi-sector-45-noida",
      " location ": " SDA-20, Near Shivalik Bank, Sector 45, Noida",
      " rating ": [
        "3.8"
      ],
      " facility ": [],
      " cuisines ": [
        "North Indian",
        "Chinese"
      ],
      " cost_for_two ": "500",
      " hour ": "6pm \u2013 4am (Mon-Sun)",
      " featured ": [],
      " discount ": [
        "10% off on all orders above \u20b9299"
      ]
    },
    "South Indian Anna Madras Cafe": {
      " url ": "https://www.zomato.com/ncr/south-indian-anna-madras-cafe-pandav-nagar-new-delhi",
      " location ": " 11, Pandav Nagar Complex, Ganesh Nagar, Pandav Nagar, New Delhi",
      " rating ": [
        "3.7",
        "3.8"
      ],
      " facility ": [],
      " cuisines ": [
        "South Indian"
      ],
      " cost_for_two ": "300",
      " hour ": "9am \u2013 10pm (Mon-Sun)",
      " featured ": [],
      " discount ": [
        "no discount"
      ]
    },
    "Food Point": {
      " url ": "https://www.zomato.com/ncr/food-point-2-rohini-new-delhi",
      " location ": " Delivery Only",
      " rating ": [],
      " facility ": [],
      " cuisines ": [
        "Chinese",
        "Fast Food"
      ],
      " cost_for_two ": "250",
      " hour ": "12:30pm \u2013 2am (Mon-Sun)",
      " featured ": [],
      " discount ": [
        "no discount"
      ]
    },
    "Bingers": {
      " url ": "https://www.zomato.com/ncr/bingers-kalkaji-new-delhi",
      " location ": " 63, Rampuri, Opposite Hanuman Mandir, Kalkaji, New Delhi",
      " rating ": [
        "3.4"
      ],
      " facility ": [],
      " cuisines ": [
        "North Indian",
        "Rolls",
        "Chinese"
      ],
      " cost_for_two ": "300",
      " hour ": "12noon \u2013 11:30pm (Mon-Sun)",
      " featured ": [],
      " discount ": [
        "no discount"
      ]
    }
  },
  {
    "Mughal Garhi": {
      " url ": "https://www.zomato.com/ncr/mughal-garhi-sector-45-noida",
      " location ": " SDA-20, Near Shivalik Bank, Sector 45, Noida",
      " rating ": [
        "3.8"
      ],
      " facility ": [],
      " cuisines ": [
        "North Indian",
        "Chinese"
      ],
      " cost_for_two ": "500",
      " hour ": "6pm \u2013 4am (Mon-Sun)",
      " featured ": [],
      " discount ": [
        "10% off on all orders above \u20b9299"
      ]
    },
    "South Indian Anna Madras Cafe": {
      " url ": "https://www.zomato.com/ncr/south-indian-anna-madras-cafe-pandav-nagar-new-delhi",
      " location ": " 11, Pandav Nagar Complex, Ganesh Nagar, Pandav Nagar, New Delhi",
      " rating ": [
        "3.7",
        "3.8"
      ],
      " facility ": [],
      " cuisines ": [
        "South Indian"
      ],
      " cost_for_two ": "300",
      " hour ": "9am \u2013 10pm (Mon-Sun)",
      " featured ": [],
      " discount ": [
        "no discount"
      ]
    },
    "Food Point": {
      " url ": "https://www.zomato.com/ncr/food-point-2-rohini-new-delhi",
      " location ": " Delivery Only",
      " rating ": [],
      " facility ": [],
      " cuisines ": [
        "Chinese",
        "Fast Food"
      ],
      " cost_for_two ": "250",
      " hour ": "12:30pm \u2013 2am (Mon-Sun)",
      " featured ": [],
      " discount ": [
        "no discount"
      ]
    },
    "Bingers": {
      " url ": "https://www.zomato.com/ncr/bingers-kalkaji-new-delhi",
      " location ": " 63, Rampuri, Opposite Hanuman Mandir, Kalkaji, New Delhi",
      " rating ": [
        "3.4"
      ],
      " facility ": [],
      " cuisines ": [
        "North Indian",
        "Rolls",
        "Chinese"
      ],
      " cost_for_two ": "300",
      " hour ": "12noon \u2013 11:30pm (Mon-Sun)",
      " featured ": [],
      " discount ": [
        "no discount"
      ]
    },
    "Leaf N Loaf": {
      " url ": "https://www.zomato.com/ncr/leaf-n-loaf-sector-23-gurgaon",
      " location ": " Shop 15, First Floor, Huda Main Market, Sector 23, Gurgaon",
      " rating ": [
        "4.6"
      ],
      " facility ": [],
      " cuisines ": [
        "Healthy Food",
        "Continental",
        "Salad",
        "Juices"
      ],
      " cost_for_two ": "700",
      " hour ": "9am \u2013 7pm (Mon-Sat),Closed (Sun)",
      " featured ": [],
      " discount ": [
        "no discount"
      ]
    }
  },
  {
    "Mughal Garhi": {
      " url ": "https://www.zomato.com/ncr/mughal-garhi-sector-45-noida",
      " location ": " SDA-20, Near Shivalik Bank, Sector 45, Noida",
      " rating ": [
        "3.8"
      ],
      " facility ": [],
      " cuisines ": [
        "North Indian",
        "Chinese"
      ],
      " cost_for_two ": "500",
      " hour ": "6pm \u2013 4am (Mon-Sun)",
      " featured ": [],
      " discount ": [
        "10% off on all orders above \u20b9299"
      ]
    },
    "South Indian Anna Madras Cafe": {
      " url ": "https://www.zomato.com/ncr/south-indian-anna-madras-cafe-pandav-nagar-new-delhi",
      " location ": " 11, Pandav Nagar Complex, Ganesh Nagar, Pandav Nagar, New Delhi",
      " rating ": [
        "3.7",
        "3.8"
      ],
      " facility ": [],
      " cuisines ": [
        "South Indian"
      ],
      " cost_for_two ": "300",
      " hour ": "9am \u2013 10pm (Mon-Sun)",
      " featured ": [],
      " discount ": [
        "no discount"
      ]
    },
    "Food Point": {
      " url ": "https://www.zomato.com/ncr/food-point-2-rohini-new-delhi",
      " location ": " Delivery Only",
      " rating ": [],
      " facility ": [],
      " cuisines ": [
        "Chinese",
        "Fast Food"
      ],
      " cost_for_two ": "250",
      " hour ": "12:30pm \u2013 2am (Mon-Sun)",
      " featured ": [],
      " discount ": [
        "no discount"
      ]
    },
    "Bingers": {
      " url ": "https://www.zomato.com/ncr/bingers-kalkaji-new-delhi",
      " location ": " 63, Rampuri, Opposite Hanuman Mandir, Kalkaji, New Delhi",
      " rating ": [
        "3.4"
      ],
      " facility ": [],
      " cuisines ": [
        "North Indian",
        "Rolls",
        "Chinese"
      ],
      " cost_for_two ": "300",
      " hour ": "12noon \u2013 11:30pm (Mon-Sun)",
      " featured ": [],
      " discount ": [
        "no discount"
      ]
    },
    "Leaf N Loaf": {
      " url ": "https://www.zomato.com/ncr/leaf-n-loaf-sector-23-gurgaon",
      " location ": " Shop 15, First Floor, Huda Main Market, Sector 23, Gurgaon",
      " rating ": [
        "4.6"
      ],
      " facility ": [],
      " cuisines ": [
        "Healthy Food",
        "Continental",
        "Salad",
        "Juices"
      ],
      " cost_for_two ": "700",
      " hour ": "9am \u2013 7pm (Mon-Sat),Closed (Sun)",
      " featured ": [],
      " discount ": [
        "no discount"
      ]
    },
    "Kebabs & Curries": {
      " url ": "https://www.zomato.com/ncr/kebabs-curries-greater-kailash-gk-1-new-delhi",
      " location ": " G-14, Bhanot Corner, R Block, Greater Kailash 1 (GK 1), New Delhi",
      " rating ": [
        "3.8"
      ],
      " facility ": [
        "Just Delivery"
      ],
      " cuisines ": [
        "North Indian",
        "Mughlai",
        "Kebab"
      ],
      " cost_for_two ": "750",
      " hour ": "11:50am \u2013 11:30pm (Mon-Sat),11:30am \u2013 11:30pm (Sun)",
      " featured ": [
        "Just Delivery"
      ],
      " discount ": [
        "no discount"
      ]
    }
  },
  {
    "Mughal Garhi": {
      " url ": "https://www.zomato.com/ncr/mughal-garhi-sector-45-noida",
      " location ": " SDA-20, Near Shivalik Bank, Sector 45, Noida",
      " rating ": [
        "3.8"
      ],
      " facility ": [],
      " cuisines ": [
        "North Indian",
        "Chinese"
      ],
      " cost_for_two ": "500",
      " hour ": "6pm \u2013 4am (Mon-Sun)",
      " featured ": [],
      " discount ": [
        "10% off on all orders above \u20b9299"
      ]
    },
    "South Indian Anna Madras Cafe": {
      " url ": "https://www.zomato.com/ncr/south-indian-anna-madras-cafe-pandav-nagar-new-delhi",
      " location ": " 11, Pandav Nagar Complex, Ganesh Nagar, Pandav Nagar, New Delhi",
      " rating ": [
        "3.7",
        "3.8"
      ],
      " facility ": [],
      " cuisines ": [
        "South Indian"
      ],
      " cost_for_two ": "300",
      " hour ": "9am \u2013 10pm (Mon-Sun)",
      " featured ": [],
      " discount ": [
        "no discount"
      ]
    },
    "Food Point": {
      " url ": "https://www.zomato.com/ncr/food-point-2-rohini-new-delhi",
      " location ": " Delivery Only",
      " rating ": [],
      " facility ": [],
      " cuisines ": [
        "Chinese",
        "Fast Food"
      ],
      " cost_for_two ": "250",
      " hour ": "12:30pm \u2013 2am (Mon-Sun)",
      " featured ": [],
      " discount ": [
        "no discount"
      ]
    },
    "Bingers": {
      " url ": "https://www.zomato.com/ncr/bingers-kalkaji-new-delhi",
      " location ": " 63, Rampuri, Opposite Hanuman Mandir, Kalkaji, New Delhi",
      " rating ": [
        "3.4"
      ],
      " facility ": [],
      " cuisines ": [
        "North Indian",
        "Rolls",
        "Chinese"
      ],
      " cost_for_two ": "300",
      " hour ": "12noon \u2013 11:30pm (Mon-Sun)",
      " featured ": [],
      " discount ": [
        "no discount"
      ]
    },
    "Leaf N Loaf": {
      " url ": "https://www.zomato.com/ncr/leaf-n-loaf-sector-23-gurgaon",
      " location ": " Shop 15, First Floor, Huda Main Market, Sector 23, Gurgaon",
      " rating ": [
        "4.6"
      ],
      " facility ": [],
      " cuisines ": [
        "Healthy Food",
        "Continental",
        "Salad",
        "Juices"
      ],
      " cost_for_two ": "700",
      " hour ": "9am \u2013 7pm (Mon-Sat),Closed (Sun)",
      " featured ": [],
      " discount ": [
        "no discount"
      ]
    },
    "Kebabs & Curries": {
      " url ": "https://www.zomato.com/ncr/kebabs-curries-greater-kailash-gk-1-new-delhi",
      " location ": " G-14, Bhanot Corner, R Block, Greater Kailash 1 (GK 1), New Delhi",
      " rating ": [
        "3.8"
      ],
      " facility ": [
        "Just Delivery"
      ],
      " cuisines ": [
        "North Indian",
        "Mughlai",
        "Kebab"
      ],
      " cost_for_two ": "750",
      " hour ": "11:50am \u2013 11:30pm (Mon-Sat),11:30am \u2013 11:30pm (Sun)",
      " featured ": [
        "Just Delivery"
      ],
      " discount ": [
        "no discount"
      ]
    },
    "24 Hours": {
      " url ": "https://www.zomato.com/ncr/24-hours-rohini-new-delhi",
      " location ": " Sector 2, Rohini, New Delhi",
      " rating ": [
        "3.2"
      ],
      " facility ": [],
      " cuisines ": [
        "Chinese",
        "North Indian",
        "Continental"
      ],
      " cost_for_two ": "400",
      " hour ": "24 Hours (Mon-Sun)",
      " featured ": [],
      " discount ": [
        "35% off on all orders above \u20b9199"
      ]
    }
  },
  {
    "Mughal Garhi": {
      " url ": "https://www.zomato.com/ncr/mughal-garhi-sector-45-noida",
      " location ": " SDA-20, Near Shivalik Bank, Sector 45, Noida",
      " rating ": [
        "3.8"
      ],
      " facility ": [],
      " cuisines ": [
        "North Indian",
        "Chinese"
      ],
      " cost_for_two ": "500",
      " hour ": "6pm \u2013 4am (Mon-Sun)",
      " featured ": [],
      " discount ": [
        "10% off on all orders above \u20b9299"
      ]
    },
    "South Indian Anna Madras Cafe": {
      " url ": "https://www.zomato.com/ncr/south-indian-anna-madras-cafe-pandav-nagar-new-delhi",
      " location ": " 11, Pandav Nagar Complex, Ganesh Nagar, Pandav Nagar, New Delhi",
      " rating ": [
        "3.7",
        "3.8"
      ],
      " facility ": [],
      " cuisines ": [
        "South Indian"
      ],
      " cost_for_two ": "300",
      " hour ": "9am \u2013 10pm (Mon-Sun)",
      " featured ": [],
      " discount ": [
        "no discount"
      ]
    },
    "Food Point": {
      " url ": "https://www.zomato.com/ncr/food-point-2-rohini-new-delhi",
      " location ": " Delivery Only",
      " rating ": [],
      " facility ": [],
      " cuisines ": [
        "Chinese",
        "Fast Food"
      ],
      " cost_for_two ": "250",
      " hour ": "12:30pm \u2013 2am (Mon-Sun)",
      " featured ": [],
      " discount ": [
        "no discount"
      ]
    },
    "Bingers": {
      " url ": "https://www.zomato.com/ncr/bingers-kalkaji-new-delhi",
      " location ": " 63, Rampuri, Opposite Hanuman Mandir, Kalkaji, New Delhi",
      " rating ": [
        "3.4"
      ],
      " facility ": [],
      " cuisines ": [
        "North Indian",
        "Rolls",
        "Chinese"
      ],
      " cost_for_two ": "300",
      " hour ": "12noon \u2013 11:30pm (Mon-Sun)",
      " featured ": [],
      " discount ": [
        "no discount"
      ]
    },
    "Leaf N Loaf": {
      " url ": "https://www.zomato.com/ncr/leaf-n-loaf-sector-23-gurgaon",
      " location ": " Shop 15, First Floor, Huda Main Market, Sector 23, Gurgaon",
      " rating ": [
        "4.6"
      ],
      " facility ": [],
      " cuisines ": [
        "Healthy Food",
        "Continental",
        "Salad",
        "Juices"
      ],
      " cost_for_two ": "700",
      " hour ": "9am \u2013 7pm (Mon-Sat),Closed (Sun)",
      " featured ": [],
      " discount ": [
        "no discount"
      ]
    },
    "Kebabs & Curries": {
      " url ": "https://www.zomato.com/ncr/kebabs-curries-greater-kailash-gk-1-new-delhi",
      " location ": " G-14, Bhanot Corner, R Block, Greater Kailash 1 (GK 1), New Delhi",
      " rating ": [
        "3.8"
      ],
      " facility ": [
        "Just Delivery"
      ],
      " cuisines ": [
        "North Indian",
        "Mughlai",
        "Kebab"
      ],
      " cost_for_two ": "750",
      " hour ": "11:50am \u2013 11:30pm (Mon-Sat),11:30am \u2013 11:30pm (Sun)",
      " featured ": [
        "Just Delivery"
      ],
      " discount ": [
        "no discount"
      ]
    },
    "24 Hours": {
      " url ": "https://www.zomato.com/ncr/24-hours-rohini-new-delhi",
      " location ": " Sector 2, Rohini, New Delhi",
      " rating ": [
        "3.2"
      ],
      " facility ": [],
      " cuisines ": [
        "Chinese",
        "North Indian",
        "Continental"
      ],
      " cost_for_two ": "400",
      " hour ": "24 Hours (Mon-Sun)",
      " featured ": [],
      " discount ": [
        "35% off on all orders above \u20b9199"
      ]
    },
    "Bikaner Sweets": {
      " url ": "https://www.zomato.com/ncr/bikaner-sweets-krishna-nagar",
      " location ": " Shop 50, Khureji Khas, Krishna Nagar, New Delhi",
      " rating ": [
        "3.6",
        "3.2"
      ],
      " facility ": [],
      " cuisines ": [
        "Mithai",
        "Chinese",
        "South Indian"
      ],
      " cost_for_two ": "200",
      " hour ": "9am \u2013 10pm (Mon, Tue, Wed, Thu, Sun), 9:01am \u2013...",
      " featured ": [],
      " discount ": [
        "no discount"
      ]
    }
  },
  {
    "Mughal Garhi": {
      " url ": "https://www.zomato.com/ncr/mughal-garhi-sector-45-noida",
      " location ": " SDA-20, Near Shivalik Bank, Sector 45, Noida",
      " rating ": [
        "3.8"
      ],
      " facility ": [],
      " cuisines ": [
        "North Indian",
        "Chinese"
      ],
      " cost_for_two ": "500",
      " hour ": "6pm \u2013 4am (Mon-Sun)",
      " featured ": [],
      " discount ": [
        "10% off on all orders above \u20b9299"
      ]
    },
    "South Indian Anna Madras Cafe": {
      " url ": "https://www.zomato.com/ncr/south-indian-anna-madras-cafe-pandav-nagar-new-delhi",
      " location ": " 11, Pandav Nagar Complex, Ganesh Nagar, Pandav Nagar, New Delhi",
      " rating ": [
        "3.7",
        "3.8"
      ],
      " facility ": [],
      " cuisines ": [
        "South Indian"
      ],
      " cost_for_two ": "300",
      " hour ": "9am \u2013 10pm (Mon-Sun)",
      " featured ": [],
      " discount ": [
        "no discount"
      ]
    },
    "Food Point": {
      " url ": "https://www.zomato.com/ncr/food-point-2-rohini-new-delhi",
      " location ": " Delivery Only",
      " rating ": [],
      " facility ": [],
      " cuisines ": [
        "Chinese",
        "Fast Food"
      ],
      " cost_for_two ": "250",
      " hour ": "12:30pm \u2013 2am (Mon-Sun)",
      " featured ": [],
      " discount ": [
        "no discount"
      ]
    },
    "Bingers": {
      " url ": "https://www.zomato.com/ncr/bingers-kalkaji-new-delhi",
      " location ": " 63, Rampuri, Opposite Hanuman Mandir, Kalkaji, New Delhi",
      " rating ": [
        "3.4"
      ],
      " facility ": [],
      " cuisines ": [
        "North Indian",
        "Rolls",
        "Chinese"
      ],
      " cost_for_two ": "300",
      " hour ": "12noon \u2013 11:30pm (Mon-Sun)",
      " featured ": [],
      " discount ": [
        "no discount"
      ]
    },
    "Leaf N Loaf": {
      " url ": "https://www.zomato.com/ncr/leaf-n-loaf-sector-23-gurgaon",
      " location ": " Shop 15, First Floor, Huda Main Market, Sector 23, Gurgaon",
      " rating ": [
        "4.6"
      ],
      " facility ": [],
      " cuisines ": [
        "Healthy Food",
        "Continental",
        "Salad",
        "Juices"
      ],
      " cost_for_two ": "700",
      " hour ": "9am \u2013 7pm (Mon-Sat),Closed (Sun)",
      " featured ": [],
      " discount ": [
        "no discount"
      ]
    },
    "Kebabs & Curries": {
      " url ": "https://www.zomato.com/ncr/kebabs-curries-greater-kailash-gk-1-new-delhi",
      " location ": " G-14, Bhanot Corner, R Block, Greater Kailash 1 (GK 1), New Delhi",
      " rating ": [
        "3.8"
      ],
      " facility ": [
        "Just Delivery"
      ],
      " cuisines ": [
        "North Indian",
        "Mughlai",
        "Kebab"
      ],
      " cost_for_two ": "750",
      " hour ": "11:50am \u2013 11:30pm (Mon-Sat),11:30am \u2013 11:30pm (Sun)",
      " featured ": [
        "Just Delivery"
      ],
      " discount ": [
        "no discount"
      ]
    },
    "24 Hours": {
      " url ": "https://www.zomato.com/ncr/24-hours-rohini-new-delhi",
      " location ": " Sector 2, Rohini, New Delhi",
      " rating ": [
        "3.2"
      ],
      " facility ": [],
      " cuisines ": [
        "Chinese",
        "North Indian",
        "Continental"
      ],
      " cost_for_two ": "400",
      " hour ": "24 Hours (Mon-Sun)",
      " featured ": [],
      " discount ": [
        "35% off on all orders above \u20b9199"
      ]
    },
    "Bikaner Sweets": {
      " url ": "https://www.zomato.com/ncr/bikaner-sweets-krishna-nagar",
      " location ": " Shop 50, Khureji Khas, Krishna Nagar, New Delhi",
      " rating ": [
        "3.6",
        "3.2"
      ],
      " facility ": [],
      " cuisines ": [
        "Mithai",
        "Chinese",
        "South Indian"
      ],
      " cost_for_two ": "200",
      " hour ": "9am \u2013 10pm (Mon, Tue, Wed, Thu, Sun), 9:01am \u2013...",
      " featured ": [],
      " discount ": [
        "no discount"
      ]
    },
    "Fried Chicken Shack": {
      " url ": "https://www.zomato.com/ncr/fried-chicken-shack-janakpuri-new-delhi",
      " location ": " G-28, Vardhaman Janak Market, A2-B, Janakpuri, New Delhi",
      " rating ": [
        "3.9"
      ],
      " facility ": [],
      " cuisines ": [
        "Fast Food"
      ],
      " cost_for_two ": "400",
      " hour ": "11am \u2013 10pm (Mon-Sun)",
      " featured ": [],
      " discount ": [
        "no discount"
      ]
    }
  },
  {
    "Mughal Garhi": {
      " url ": "https://www.zomato.com/ncr/mughal-garhi-sector-45-noida",
      " location ": " SDA-20, Near Shivalik Bank, Sector 45, Noida",
      " rating ": [
        "3.8"
      ],
      " facility ": [],
      " cuisines ": [
        "North Indian",
        "Chinese"
      ],
      " cost_for_two ": "500",
      " hour ": "6pm \u2013 4am (Mon-Sun)",
      " featured ": [],
      " discount ": [
        "10% off on all orders above \u20b9299"
      ]
    },
    "South Indian Anna Madras Cafe": {
      " url ": "https://www.zomato.com/ncr/south-indian-anna-madras-cafe-pandav-nagar-new-delhi",
      " location ": " 11, Pandav Nagar Complex, Ganesh Nagar, Pandav Nagar, New Delhi",
      " rating ": [
        "3.7",
        "3.8"
      ],
      " facility ": [],
      " cuisines ": [
        "South Indian"
      ],
      " cost_for_two ": "300",
      " hour ": "9am \u2013 10pm (Mon-Sun)",
      " featured ": [],
      " discount ": [
        "no discount"
      ]
    },
    "Food Point": {
      " url ": "https://www.zomato.com/ncr/food-point-2-rohini-new-delhi",
      " location ": " Delivery Only",
      " rating ": [],
      " facility ": [],
      " cuisines ": [
        "Chinese",
        "Fast Food"
      ],
      " cost_for_two ": "250",
      " hour ": "12:30pm \u2013 2am (Mon-Sun)",
      " featured ": [],
      " discount ": [
        "no discount"
      ]
    },
    "Bingers": {
      " url ": "https://www.zomato.com/ncr/bingers-kalkaji-new-delhi",
      " location ": " 63, Rampuri, Opposite Hanuman Mandir, Kalkaji, New Delhi",
      " rating ": [
        "3.4"
      ],
      " facility ": [],
      " cuisines ": [
        "North Indian",
        "Rolls",
        "Chinese"
      ],
      " cost_for_two ": "300",
      " hour ": "12noon \u2013 11:30pm (Mon-Sun)",
      " featured ": [],
      " discount ": [
        "no discount"
      ]
    },
    "Leaf N Loaf": {
      " url ": "https://www.zomato.com/ncr/leaf-n-loaf-sector-23-gurgaon",
      " location ": " Shop 15, First Floor, Huda Main Market, Sector 23, Gurgaon",
      " rating ": [
        "4.6"
      ],
      " facility ": [],
      " cuisines ": [
        "Healthy Food",
        "Continental",
        "Salad",
        "Juices"
      ],
      " cost_for_two ": "700",
      " hour ": "9am \u2013 7pm (Mon-Sat),Closed (Sun)",
      " featured ": [],
      " discount ": [
        "no discount"
      ]
    },
    "Kebabs & Curries": {
      " url ": "https://www.zomato.com/ncr/kebabs-curries-greater-kailash-gk-1-new-delhi",
      " location ": " G-14, Bhanot Corner, R Block, Greater Kailash 1 (GK 1), New Delhi",
      " rating ": [
        "3.8"
      ],
      " facility ": [
        "Just Delivery"
      ],
      " cuisines ": [
        "North Indian",
        "Mughlai",
        "Kebab"
      ],
      " cost_for_two ": "750",
      " hour ": "11:50am \u2013 11:30pm (Mon-Sat),11:30am \u2013 11:30pm (Sun)",
      " featured ": [
        "Just Delivery"
      ],
      " discount ": [
        "no discount"
      ]
    },
    "24 Hours": {
      " url ": "https://www.zomato.com/ncr/24-hours-rohini-new-delhi",
      " location ": " Sector 2, Rohini, New Delhi",
      " rating ": [
        "3.2"
      ],
      " facility ": [],
      " cuisines ": [
        "Chinese",
        "North Indian",
        "Continental"
      ],
      " cost_for_two ": "400",
      " hour ": "24 Hours (Mon-Sun)",
      " featured ": [],
      " discount ": [
        "35% off on all orders above \u20b9199"
      ]
    },
    "Bikaner Sweets": {
      " url ": "https://www.zomato.com/ncr/bikaner-sweets-krishna-nagar",
      " location ": " Shop 50, Khureji Khas, Krishna Nagar, New Delhi",
      " rating ": [
        "3.6",
        "3.2"
      ],
      " facility ": [],
      " cuisines ": [
        "Mithai",
        "Chinese",
        "South Indian"
      ],
      " cost_for_two ": "200",
      " hour ": "9am \u2013 10pm (Mon, Tue, Wed, Thu, Sun), 9:01am \u2013...",
      " featured ": [],
      " discount ": [
        "no discount"
      ]
    },
    "Fried Chicken Shack": {
      " url ": "https://www.zomato.com/ncr/fried-chicken-shack-janakpuri-new-delhi",
      " location ": " G-28, Vardhaman Janak Market, A2-B, Janakpuri, New Delhi",
      " rating ": [
        "3.9"
      ],
      " facility ": [],
      " cuisines ": [
        "Fast Food"
      ],
      " cost_for_two ": "400",
      " hour ": "11am \u2013 10pm (Mon-Sun)",
      " featured ": [],
      " discount ": [
        "no discount"
      ]
    },
    "Prince of China": {
      " url ": "https://www.zomato.com/ncr/prince-of-china-kalkaji-new-delhi",
      " location ": " 31-A, Krishna Market, Opposite Deshbandhu College, Kalkaji, New Delhi",
      " rating ": [
        "3.8"
      ],
      " facility ": [],
      " cuisines ": [
        "Chinese",
        "Seafood",
        "Thai"
      ],
      " cost_for_two ": "800",
      " hour ": "11:30am \u2013 11pm (Mon-Sun)",
      " featured ": [],
      " discount ": [
        "no discount"
      ]
    }
  },
  {
    "Mughal Garhi": {
      " url ": "https://www.zomato.com/ncr/mughal-garhi-sector-45-noida",
      " location ": " SDA-20, Near Shivalik Bank, Sector 45, Noida",
      " rating ": [
        "3.8"
      ],
      " facility ": [],
      " cuisines ": [
        "North Indian",
        "Chinese"
      ],
      " cost_for_two ": "500",
      " hour ": "6pm \u2013 4am (Mon-Sun)",
      " featured ": [],
      " discount ": [
        "10% off on all orders above \u20b9299"
      ]
    },
    "South Indian Anna Madras Cafe": {
      " url ": "https://www.zomato.com/ncr/south-indian-anna-madras-cafe-pandav-nagar-new-delhi",
      " location ": " 11, Pandav Nagar Complex, Ganesh Nagar, Pandav Nagar, New Delhi",
      " rating ": [
        "3.7",
        "3.8"
      ],
      " facility ": [],
      " cuisines ": [
        "South Indian"
      ],
      " cost_for_two ": "300",
      " hour ": "9am \u2013 10pm (Mon-Sun)",
      " featured ": [],
      " discount ": [
        "no discount"
      ]
    },
    "Food Point": {
      " url ": "https://www.zomato.com/ncr/food-point-2-rohini-new-delhi",
      " location ": " Delivery Only",
      " rating ": [],
      " facility ": [],
      " cuisines ": [
        "Chinese",
        "Fast Food"
      ],
      " cost_for_two ": "250",
      " hour ": "12:30pm \u2013 2am (Mon-Sun)",
      " featured ": [],
      " discount ": [
        "no discount"
      ]
    },
    "Bingers": {
      " url ": "https://www.zomato.com/ncr/bingers-kalkaji-new-delhi",
      " location ": " 63, Rampuri, Opposite Hanuman Mandir, Kalkaji, New Delhi",
      " rating ": [
        "3.4"
      ],
      " facility ": [],
      " cuisines ": [
        "North Indian",
        "Rolls",
        "Chinese"
      ],
      " cost_for_two ": "300",
      " hour ": "12noon \u2013 11:30pm (Mon-Sun)",
      " featured ": [],
      " discount ": [
        "no discount"
      ]
    },
    "Leaf N Loaf": {
      " url ": "https://www.zomato.com/ncr/leaf-n-loaf-sector-23-gurgaon",
      " location ": " Shop 15, First Floor, Huda Main Market, Sector 23, Gurgaon",
      " rating ": [
        "4.6"
      ],
      " facility ": [],
      " cuisines ": [
        "Healthy Food",
        "Continental",
        "Salad",
        "Juices"
      ],
      " cost_for_two ": "700",
      " hour ": "9am \u2013 7pm (Mon-Sat),Closed (Sun)",
      " featured ": [],
      " discount ": [
        "no discount"
      ]
    },
    "Kebabs & Curries": {
      " url ": "https://www.zomato.com/ncr/kebabs-curries-greater-kailash-gk-1-new-delhi",
      " location ": " G-14, Bhanot Corner, R Block, Greater Kailash 1 (GK 1), New Delhi",
      " rating ": [
        "3.8"
      ],
      " facility ": [
        "Just Delivery"
      ],
      " cuisines ": [
        "North Indian",
        "Mughlai",
        "Kebab"
      ],
      " cost_for_two ": "750",
      " hour ": "11:50am \u2013 11:30pm (Mon-Sat),11:30am \u2013 11:30pm (Sun)",
      " featured ": [
        "Just Delivery"
      ],
      " discount ": [
        "no discount"
      ]
    },
    "24 Hours": {
      " url ": "https://www.zomato.com/ncr/24-hours-rohini-new-delhi",
      " location ": " Sector 2, Rohini, New Delhi",
      " rating ": [
        "3.2"
      ],
      " facility ": [],
      " cuisines ": [
        "Chinese",
        "North Indian",
        "Continental"
      ],
      " cost_for_two ": "400",
      " hour ": "24 Hours (Mon-Sun)",
      " featured ": [],
      " discount ": [
        "35% off on all orders above \u20b9199"
      ]
    },
    "Bikaner Sweets": {
      " url ": "https://www.zomato.com/ncr/bikaner-sweets-krishna-nagar",
      " location ": " Shop 50, Khureji Khas, Krishna Nagar, New Delhi",
      " rating ": [
        "3.6",
        "3.2"
      ],
      " facility ": [],
      " cuisines ": [
        "Mithai",
        "Chinese",
        "South Indian"
      ],
      " cost_for_two ": "200",
      " hour ": "9am \u2013 10pm (Mon, Tue, Wed, Thu, Sun), 9:01am \u2013...",
      " featured ": [],
      " discount ": [
        "no discount"
      ]
    },
    "Fried Chicken Shack": {
      " url ": "https://www.zomato.com/ncr/fried-chicken-shack-janakpuri-new-delhi",
      " location ": " G-28, Vardhaman Janak Market, A2-B, Janakpuri, New Delhi",
      " rating ": [
        "3.9"
      ],
      " facility ": [],
      " cuisines ": [
        "Fast Food"
      ],
      " cost_for_two ": "400",
      " hour ": "11am \u2013 10pm (Mon-Sun)",
      " featured ": [],
      " discount ": [
        "no discount"
      ]
    },
    "Prince of China": {
      " url ": "https://www.zomato.com/ncr/prince-of-china-kalkaji-new-delhi",
      " location ": " 31-A, Krishna Market, Opposite Deshbandhu College, Kalkaji, New Delhi",
      " rating ": [
        "3.8"
      ],
      " facility ": [],
      " cuisines ": [
        "Chinese",
        "Seafood",
        "Thai"
      ],
      " cost_for_two ": "800",
      " hour ": "11:30am \u2013 11pm (Mon-Sun)",
      " featured ": [],
      " discount ": [
        "no discount"
      ]
    },
    "Cake Time": {
      " url ": "https://www.zomato.com/ncr/cake-time-kalkaji-new-delhi",
      " location ": " J 3/143 DDA, Kalkaji, New Delhi",
      " rating ": [
        "4.3"
      ],
      " facility ": [],
      " cuisines ": [
        "Bakery",
        "Fast Food"
      ],
      " cost_for_two ": "300",
      " hour ": "10am \u2013 10:30pm (Mon-Sun)",
      " featured ": [],
      " discount ": [
        "no discount"
      ]
    }
  },
  {
    "Mughal Garhi": {
      " url ": "https://www.zomato.com/ncr/mughal-garhi-sector-45-noida",
      " location ": " SDA-20, Near Shivalik Bank, Sector 45, Noida",
      " rating ": [
        "3.8"
      ],
      " facility ": [],
      " cuisines ": [
        "North Indian",
        "Chinese"
      ],
      " cost_for_two ": "500",
      " hour ": "6pm \u2013 4am (Mon-Sun)",
      " featured ": [],
      " discount ": [
        "10% off on all orders above \u20b9299"
      ]
    },
    "South Indian Anna Madras Cafe": {
      " url ": "https://www.zomato.com/ncr/south-indian-anna-madras-cafe-pandav-nagar-new-delhi",
      " location ": " 11, Pandav Nagar Complex, Ganesh Nagar, Pandav Nagar, New Delhi",
      " rating ": [
        "3.7",
        "3.8"
      ],
      " facility ": [],
      " cuisines ": [
        "South Indian"
      ],
      " cost_for_two ": "300",
      " hour ": "9am \u2013 10pm (Mon-Sun)",
      " featured ": [],
      " discount ": [
        "no discount"
      ]
    },
    "Food Point": {
      " url ": "https://www.zomato.com/ncr/food-point-2-rohini-new-delhi",
      " location ": " Delivery Only",
      " rating ": [],
      " facility ": [],
      " cuisines ": [
        "Chinese",
        "Fast Food"
      ],
      " cost_for_two ": "250",
      " hour ": "12:30pm \u2013 2am (Mon-Sun)",
      " featured ": [],
      " discount ": [
        "no discount"
      ]
    },
    "Bingers": {
      " url ": "https://www.zomato.com/ncr/bingers-kalkaji-new-delhi",
      " location ": " 63, Rampuri, Opposite Hanuman Mandir, Kalkaji, New Delhi",
      " rating ": [
        "3.4"
      ],
      " facility ": [],
      " cuisines ": [
        "North Indian",
        "Rolls",
        "Chinese"
      ],
      " cost_for_two ": "300",
      " hour ": "12noon \u2013 11:30pm (Mon-Sun)",
      " featured ": [],
      " discount ": [
        "no discount"
      ]
    },
    "Leaf N Loaf": {
      " url ": "https://www.zomato.com/ncr/leaf-n-loaf-sector-23-gurgaon",
      " location ": " Shop 15, First Floor, Huda Main Market, Sector 23, Gurgaon",
      " rating ": [
        "4.6"
      ],
      " facility ": [],
      " cuisines ": [
        "Healthy Food",
        "Continental",
        "Salad",
        "Juices"
      ],
      " cost_for_two ": "700",
      " hour ": "9am \u2013 7pm (Mon-Sat),Closed (Sun)",
      " featured ": [],
      " discount ": [
        "no discount"
      ]
    },
    "Kebabs & Curries": {
      " url ": "https://www.zomato.com/ncr/kebabs-curries-greater-kailash-gk-1-new-delhi",
      " location ": " G-14, Bhanot Corner, R Block, Greater Kailash 1 (GK 1), New Delhi",
      " rating ": [
        "3.8"
      ],
      " facility ": [
        "Just Delivery"
      ],
      " cuisines ": [
        "North Indian",
        "Mughlai",
        "Kebab"
      ],
      " cost_for_two ": "750",
      " hour ": "11:50am \u2013 11:30pm (Mon-Sat),11:30am \u2013 11:30pm (Sun)",
      " featured ": [
        "Just Delivery"
      ],
      " discount ": [
        "no discount"
      ]
    },
    "24 Hours": {
      " url ": "https://www.zomato.com/ncr/24-hours-rohini-new-delhi",
      " location ": " Sector 2, Rohini, New Delhi",
      " rating ": [
        "3.2"
      ],
      " facility ": [],
      " cuisines ": [
        "Chinese",
        "North Indian",
        "Continental"
      ],
      " cost_for_two ": "400",
      " hour ": "24 Hours (Mon-Sun)",
      " featured ": [],
      " discount ": [
        "35% off on all orders above \u20b9199"
      ]
    },
    "Bikaner Sweets": {
      " url ": "https://www.zomato.com/ncr/bikaner-sweets-krishna-nagar",
      " location ": " Shop 50, Khureji Khas, Krishna Nagar, New Delhi",
      " rating ": [
        "3.6",
        "3.2"
      ],
      " facility ": [],
      " cuisines ": [
        "Mithai",
        "Chinese",
        "South Indian"
      ],
      " cost_for_two ": "200",
      " hour ": "9am \u2013 10pm (Mon, Tue, Wed, Thu, Sun), 9:01am \u2013...",
      " featured ": [],
      " discount ": [
        "no discount"
      ]
    },
    "Fried Chicken Shack": {
      " url ": "https://www.zomato.com/ncr/fried-chicken-shack-janakpuri-new-delhi",
      " location ": " G-28, Vardhaman Janak Market, A2-B, Janakpuri, New Delhi",
      " rating ": [
        "3.9"
      ],
      " facility ": [],
      " cuisines ": [
        "Fast Food"
      ],
      " cost_for_two ": "400",
      " hour ": "11am \u2013 10pm (Mon-Sun)",
      " featured ": [],
      " discount ": [
        "no discount"
      ]
    },
    "Prince of China": {
      " url ": "https://www.zomato.com/ncr/prince-of-china-kalkaji-new-delhi",
      " location ": " 31-A, Krishna Market, Opposite Deshbandhu College, Kalkaji, New Delhi",
      " rating ": [
        "3.8"
      ],
      " facility ": [],
      " cuisines ": [
        "Chinese",
        "Seafood",
        "Thai"
      ],
      " cost_for_two ": "800",
      " hour ": "11:30am \u2013 11pm (Mon-Sun)",
      " featured ": [],
      " discount ": [
        "no discount"
      ]
    },
    "Cake Time": {
      " url ": "https://www.zomato.com/ncr/cake-time-kalkaji-new-delhi",
      " location ": " J 3/143 DDA, Kalkaji, New Delhi",
      " rating ": [
        "4.3"
      ],
      " facility ": [],
      " cuisines ": [
        "Bakery",
        "Fast Food"
      ],
      " cost_for_two ": "300",
      " hour ": "10am \u2013 10:30pm (Mon-Sun)",
      " featured ": [],
      " discount ": [
        "no discount"
      ]
    },
    "New Durga Corner": {
      " url ": "https://www.zomato.com/ncr/new-durga-corner-paschim-vihar-new-delhi",
      " location ": " Shop 3, A-5B, DDA Market, Paschim Vihar, New Delhi",
      " rating ": [
        "3.8",
        "4.1"
      ],
      " facility ": [],
      " cuisines ": [
        "South Indian"
      ],
      " cost_for_two ": "300",
      " hour ": "10am \u2013 10:30pm (Mon-Sun)",
      " featured ": [],
      " discount ": [
        "10% off on all orders above \u20b999"
      ]
    }
  },
  {
    "Mughal Garhi": {
      " url ": "https://www.zomato.com/ncr/mughal-garhi-sector-45-noida",
      " location ": " SDA-20, Near Shivalik Bank, Sector 45, Noida",
      " rating ": [
        "3.8"
      ],
      " facility ": [],
      " cuisines ": [
        "North Indian",
        "Chinese"
      ],
      " cost_for_two ": "500",
      " hour ": "6pm \u2013 4am (Mon-Sun)",
      " featured ": [],
      " discount ": [
        "10% off on all orders above \u20b9299"
      ]
    },
    "South Indian Anna Madras Cafe": {
      " url ": "https://www.zomato.com/ncr/south-indian-anna-madras-cafe-pandav-nagar-new-delhi",
      " location ": " 11, Pandav Nagar Complex, Ganesh Nagar, Pandav Nagar, New Delhi",
      " rating ": [
        "3.7",
        "3.8"
      ],
      " facility ": [],
      " cuisines ": [
        "South Indian"
      ],
      " cost_for_two ": "300",
      " hour ": "9am \u2013 10pm (Mon-Sun)",
      " featured ": [],
      " discount ": [
        "no discount"
      ]
    },
    "Food Point": {
      " url ": "https://www.zomato.com/ncr/food-point-2-rohini-new-delhi",
      " location ": " Delivery Only",
      " rating ": [],
      " facility ": [],
      " cuisines ": [
        "Chinese",
        "Fast Food"
      ],
      " cost_for_two ": "250",
      " hour ": "12:30pm \u2013 2am (Mon-Sun)",
      " featured ": [],
      " discount ": [
        "no discount"
      ]
    },
    "Bingers": {
      " url ": "https://www.zomato.com/ncr/bingers-kalkaji-new-delhi",
      " location ": " 63, Rampuri, Opposite Hanuman Mandir, Kalkaji, New Delhi",
      " rating ": [
        "3.4"
      ],
      " facility ": [],
      " cuisines ": [
        "North Indian",
        "Rolls",
        "Chinese"
      ],
      " cost_for_two ": "300",
      " hour ": "12noon \u2013 11:30pm (Mon-Sun)",
      " featured ": [],
      " discount ": [
        "no discount"
      ]
    },
    "Leaf N Loaf": {
      " url ": "https://www.zomato.com/ncr/leaf-n-loaf-sector-23-gurgaon",
      " location ": " Shop 15, First Floor, Huda Main Market, Sector 23, Gurgaon",
      " rating ": [
        "4.6"
      ],
      " facility ": [],
      " cuisines ": [
        "Healthy Food",
        "Continental",
        "Salad",
        "Juices"
      ],
      " cost_for_two ": "700",
      " hour ": "9am \u2013 7pm (Mon-Sat),Closed (Sun)",
      " featured ": [],
      " discount ": [
        "no discount"
      ]
    },
    "Kebabs & Curries": {
      " url ": "https://www.zomato.com/ncr/kebabs-curries-greater-kailash-gk-1-new-delhi",
      " location ": " G-14, Bhanot Corner, R Block, Greater Kailash 1 (GK 1), New Delhi",
      " rating ": [
        "3.8"
      ],
      " facility ": [
        "Just Delivery"
      ],
      " cuisines ": [
        "North Indian",
        "Mughlai",
        "Kebab"
      ],
      " cost_for_two ": "750",
      " hour ": "11:50am \u2013 11:30pm (Mon-Sat),11:30am \u2013 11:30pm (Sun)",
      " featured ": [
        "Just Delivery"
      ],
      " discount ": [
        "no discount"
      ]
    },
    "24 Hours": {
      " url ": "https://www.zomato.com/ncr/24-hours-rohini-new-delhi",
      " location ": " Sector 2, Rohini, New Delhi",
      " rating ": [
        "3.2"
      ],
      " facility ": [],
      " cuisines ": [
        "Chinese",
        "North Indian",
        "Continental"
      ],
      " cost_for_two ": "400",
      " hour ": "24 Hours (Mon-Sun)",
      " featured ": [],
      " discount ": [
        "35% off on all orders above \u20b9199"
      ]
    },
    "Bikaner Sweets": {
      " url ": "https://www.zomato.com/ncr/bikaner-sweets-krishna-nagar",
      " location ": " Shop 50, Khureji Khas, Krishna Nagar, New Delhi",
      " rating ": [
        "3.6",
        "3.2"
      ],
      " facility ": [],
      " cuisines ": [
        "Mithai",
        "Chinese",
        "South Indian"
      ],
      " cost_for_two ": "200",
      " hour ": "9am \u2013 10pm (Mon, Tue, Wed, Thu, Sun), 9:01am \u2013...",
      " featured ": [],
      " discount ": [
        "no discount"
      ]
    },
    "Fried Chicken Shack": {
      " url ": "https://www.zomato.com/ncr/fried-chicken-shack-janakpuri-new-delhi",
      " location ": " G-28, Vardhaman Janak Market, A2-B, Janakpuri, New Delhi",
      " rating ": [
        "3.9"
      ],
      " facility ": [],
      " cuisines ": [
        "Fast Food"
      ],
      " cost_for_two ": "400",
      " hour ": "11am \u2013 10pm (Mon-Sun)",
      " featured ": [],
      " discount ": [
        "no discount"
      ]
    },
    "Prince of China": {
      " url ": "https://www.zomato.com/ncr/prince-of-china-kalkaji-new-delhi",
      " location ": " 31-A, Krishna Market, Opposite Deshbandhu College, Kalkaji, New Delhi",
      " rating ": [
        "3.8"
      ],
      " facility ": [],
      " cuisines ": [
        "Chinese",
        "Seafood",
        "Thai"
      ],
      " cost_for_two ": "800",
      " hour ": "11:30am \u2013 11pm (Mon-Sun)",
      " featured ": [],
      " discount ": [
        "no discount"
      ]
    },
    "Cake Time": {
      " url ": "https://www.zomato.com/ncr/cake-time-kalkaji-new-delhi",
      " location ": " J 3/143 DDA, Kalkaji, New Delhi",
      " rating ": [
        "4.3"
      ],
      " facility ": [],
      " cuisines ": [
        "Bakery",
        "Fast Food"
      ],
      " cost_for_two ": "300",
      " hour ": "10am \u2013 10:30pm (Mon-Sun)",
      " featured ": [],
      " discount ": [
        "no discount"
      ]
    },
    "New Durga Corner": {
      " url ": "https://www.zomato.com/ncr/new-durga-corner-paschim-vihar-new-delhi",
      " location ": " Shop 3, A-5B, DDA Market, Paschim Vihar, New Delhi",
      " rating ": [
        "3.8",
        "4.1"
      ],
      " facility ": [],
      " cuisines ": [
        "South Indian"
      ],
      " cost_for_two ": "300",
      " hour ": "10am \u2013 10:30pm (Mon-Sun)",
      " featured ": [],
      " discount ": [
        "10% off on all orders above \u20b999"
      ]
    },
    "Pizza King Express": {
      " url ": "https://www.zomato.com/ncr/pizza-king-express-1-ballabhgarh-faridabad",
      " location ": " Plot 17, B Block, 33 Feet Road, Bhagat Singh Colony, Ballabhgarh, Faridabad",
      " rating ": [
        "3.8",
        "4.0"
      ],
      " facility ": [],
      " cuisines ": [
        "Pizza",
        "Fast Food"
      ],
      " cost_for_two ": "400",
      " hour ": "10am \u2013 10pm (Mon-Sun)",
      " featured ": [],
      " discount ": [
        "no discount"
      ]
    }
  },
  {
    "Mughal Garhi": {
      " url ": "https://www.zomato.com/ncr/mughal-garhi-sector-45-noida",
      " location ": " SDA-20, Near Shivalik Bank, Sector 45, Noida",
      " rating ": [
        "3.8"
      ],
      " facility ": [],
      " cuisines ": [
        "North Indian",
        "Chinese"
      ],
      " cost_for_two ": "500",
      " hour ": "6pm \u2013 4am (Mon-Sun)",
      " featured ": [],
      " discount ": [
        "10% off on all orders above \u20b9299"
      ]
    },
    "South Indian Anna Madras Cafe": {
      " url ": "https://www.zomato.com/ncr/south-indian-anna-madras-cafe-pandav-nagar-new-delhi",
      " location ": " 11, Pandav Nagar Complex, Ganesh Nagar, Pandav Nagar, New Delhi",
      " rating ": [
        "3.7",
        "3.8"
      ],
      " facility ": [],
      " cuisines ": [
        "South Indian"
      ],
      " cost_for_two ": "300",
      " hour ": "9am \u2013 10pm (Mon-Sun)",
      " featured ": [],
      " discount ": [
        "no discount"
      ]
    },
    "Food Point": {
      " url ": "https://www.zomato.com/ncr/food-point-2-rohini-new-delhi",
      " location ": " Delivery Only",
      " rating ": [],
      " facility ": [],
      " cuisines ": [
        "Chinese",
        "Fast Food"
      ],
      " cost_for_two ": "250",
      " hour ": "12:30pm \u2013 2am (Mon-Sun)",
      " featured ": [],
      " discount ": [
        "no discount"
      ]
    },
    "Bingers": {
      " url ": "https://www.zomato.com/ncr/bingers-kalkaji-new-delhi",
      " location ": " 63, Rampuri, Opposite Hanuman Mandir, Kalkaji, New Delhi",
      " rating ": [
        "3.4"
      ],
      " facility ": [],
      " cuisines ": [
        "North Indian",
        "Rolls",
        "Chinese"
      ],
      " cost_for_two ": "300",
      " hour ": "12noon \u2013 11:30pm (Mon-Sun)",
      " featured ": [],
      " discount ": [
        "no discount"
      ]
    },
    "Leaf N Loaf": {
      " url ": "https://www.zomato.com/ncr/leaf-n-loaf-sector-23-gurgaon",
      " location ": " Shop 15, First Floor, Huda Main Market, Sector 23, Gurgaon",
      " rating ": [
        "4.6"
      ],
      " facility ": [],
      " cuisines ": [
        "Healthy Food",
        "Continental",
        "Salad",
        "Juices"
      ],
      " cost_for_two ": "700",
      " hour ": "9am \u2013 7pm (Mon-Sat),Closed (Sun)",
      " featured ": [],
      " discount ": [
        "no discount"
      ]
    },
    "Kebabs & Curries": {
      " url ": "https://www.zomato.com/ncr/kebabs-curries-greater-kailash-gk-1-new-delhi",
      " location ": " G-14, Bhanot Corner, R Block, Greater Kailash 1 (GK 1), New Delhi",
      " rating ": [
        "3.8"
      ],
      " facility ": [
        "Just Delivery"
      ],
      " cuisines ": [
        "North Indian",
        "Mughlai",
        "Kebab"
      ],
      " cost_for_two ": "750",
      " hour ": "11:50am \u2013 11:30pm (Mon-Sat),11:30am \u2013 11:30pm (Sun)",
      " featured ": [
        "Just Delivery"
      ],
      " discount ": [
        "no discount"
      ]
    },
    "24 Hours": {
      " url ": "https://www.zomato.com/ncr/24-hours-rohini-new-delhi",
      " location ": " Sector 2, Rohini, New Delhi",
      " rating ": [
        "3.2"
      ],
      " facility ": [],
      " cuisines ": [
        "Chinese",
        "North Indian",
        "Continental"
      ],
      " cost_for_two ": "400",
      " hour ": "24 Hours (Mon-Sun)",
      " featured ": [],
      " discount ": [
        "35% off on all orders above \u20b9199"
      ]
    },
    "Bikaner Sweets": {
      " url ": "https://www.zomato.com/ncr/bikaner-sweets-krishna-nagar",
      " location ": " Shop 50, Khureji Khas, Krishna Nagar, New Delhi",
      " rating ": [
        "3.6",
        "3.2"
      ],
      " facility ": [],
      " cuisines ": [
        "Mithai",
        "Chinese",
        "South Indian"
      ],
      " cost_for_two ": "200",
      " hour ": "9am \u2013 10pm (Mon, Tue, Wed, Thu, Sun), 9:01am \u2013...",
      " featured ": [],
      " discount ": [
        "no discount"
      ]
    },
    "Fried Chicken Shack": {
      " url ": "https://www.zomato.com/ncr/fried-chicken-shack-janakpuri-new-delhi",
      " location ": " G-28, Vardhaman Janak Market, A2-B, Janakpuri, New Delhi",
      " rating ": [
        "3.9"
      ],
      " facility ": [],
      " cuisines ": [
        "Fast Food"
      ],
      " cost_for_two ": "400",
      " hour ": "11am \u2013 10pm (Mon-Sun)",
      " featured ": [],
      " discount ": [
        "no discount"
      ]
    },
    "Prince of China": {
      " url ": "https://www.zomato.com/ncr/prince-of-china-kalkaji-new-delhi",
      " location ": " 31-A, Krishna Market, Opposite Deshbandhu College, Kalkaji, New Delhi",
      " rating ": [
        "3.8"
      ],
      " facility ": [],
      " cuisines ": [
        "Chinese",
        "Seafood",
        "Thai"
      ],
      " cost_for_two ": "800",
      " hour ": "11:30am \u2013 11pm (Mon-Sun)",
      " featured ": [],
      " discount ": [
        "no discount"
      ]
    },
    "Cake Time": {
      " url ": "https://www.zomato.com/ncr/cake-time-kalkaji-new-delhi",
      " location ": " J 3/143 DDA, Kalkaji, New Delhi",
      " rating ": [
        "4.3"
      ],
      " facility ": [],
      " cuisines ": [
        "Bakery",
        "Fast Food"
      ],
      " cost_for_two ": "300",
      " hour ": "10am \u2013 10:30pm (Mon-Sun)",
      " featured ": [],
      " discount ": [
        "no discount"
      ]
    },
    "New Durga Corner": {
      " url ": "https://www.zomato.com/ncr/new-durga-corner-paschim-vihar-new-delhi",
      " location ": " Shop 3, A-5B, DDA Market, Paschim Vihar, New Delhi",
      " rating ": [
        "3.8",
        "4.1"
      ],
      " facility ": [],
      " cuisines ": [
        "South Indian"
      ],
      " cost_for_two ": "300",
      " hour ": "10am \u2013 10:30pm (Mon-Sun)",
      " featured ": [],
      " discount ": [
        "10% off on all orders above \u20b999"
      ]
    },
    "Pizza King Express": {
      " url ": "https://www.zomato.com/ncr/pizza-king-express-1-ballabhgarh-faridabad",
      " location ": " Plot 17, B Block, 33 Feet Road, Bhagat Singh Colony, Ballabhgarh, Faridabad",
      " rating ": [
        "3.8",
        "4.0"
      ],
      " facility ": [],
      " cuisines ": [
        "Pizza",
        "Fast Food"
      ],
      " cost_for_two ": "400",
      " hour ": "10am \u2013 10pm (Mon-Sun)",
      " featured ": [],
      " discount ": [
        "no discount"
      ]
    },
    "Shri Rama Restaurant": {
      " url ": "https://www.zomato.com/ncr/shri-rama-restaurant-karol-bagh-new-delhi",
      " location ": " 21-B/1, New Rohtak Road, Karol Bagh, New Delhi",
      " rating ": [
        "3.8",
        "3.9"
      ],
      " facility ": [],
      " cuisines ": [
        "North Indian",
        "Chinese",
        "Mughlai"
      ],
      " cost_for_two ": "550",
      " hour ": "12noon \u2013 4:30pm, 6:30pm \u2013 12midnight (Mon-Sun)",
      " featured ": [],
      " discount ": [
        "no discount"
      ]
    }
  },
  {
    "Mughal Garhi": {
      " url ": "https://www.zomato.com/ncr/mughal-garhi-sector-45-noida",
      " location ": " SDA-20, Near Shivalik Bank, Sector 45, Noida",
      " rating ": [
        "3.8"
      ],
      " facility ": [],
      " cuisines ": [
        "North Indian",
        "Chinese"
      ],
      " cost_for_two ": "500",
      " hour ": "6pm \u2013 4am (Mon-Sun)",
      " featured ": [],
      " discount ": [
        "10% off on all orders above \u20b9299"
      ]
    },
    "South Indian Anna Madras Cafe": {
      " url ": "https://www.zomato.com/ncr/south-indian-anna-madras-cafe-pandav-nagar-new-delhi",
      " location ": " 11, Pandav Nagar Complex, Ganesh Nagar, Pandav Nagar, New Delhi",
      " rating ": [
        "3.7",
        "3.8"
      ],
      " facility ": [],
      " cuisines ": [
        "South Indian"
      ],
      " cost_for_two ": "300",
      " hour ": "9am \u2013 10pm (Mon-Sun)",
      " featured ": [],
      " discount ": [
        "no discount"
      ]
    },
    "Food Point": {
      " url ": "https://www.zomato.com/ncr/food-point-2-rohini-new-delhi",
      " location ": " Delivery Only",
      " rating ": [],
      " facility ": [],
      " cuisines ": [
        "Chinese",
        "Fast Food"
      ],
      " cost_for_two ": "250",
      " hour ": "12:30pm \u2013 2am (Mon-Sun)",
      " featured ": [],
      " discount ": [
        "no discount"
      ]
    },
    "Bingers": {
      " url ": "https://www.zomato.com/ncr/bingers-kalkaji-new-delhi",
      " location ": " 63, Rampuri, Opposite Hanuman Mandir, Kalkaji, New Delhi",
      " rating ": [
        "3.4"
      ],
      " facility ": [],
      " cuisines ": [
        "North Indian",
        "Rolls",
        "Chinese"
      ],
      " cost_for_two ": "300",
      " hour ": "12noon \u2013 11:30pm (Mon-Sun)",
      " featured ": [],
      " discount ": [
        "no discount"
      ]
    },
    "Leaf N Loaf": {
      " url ": "https://www.zomato.com/ncr/leaf-n-loaf-sector-23-gurgaon",
      " location ": " Shop 15, First Floor, Huda Main Market, Sector 23, Gurgaon",
      " rating ": [
        "4.6"
      ],
      " facility ": [],
      " cuisines ": [
        "Healthy Food",
        "Continental",
        "Salad",
        "Juices"
      ],
      " cost_for_two ": "700",
      " hour ": "9am \u2013 7pm (Mon-Sat),Closed (Sun)",
      " featured ": [],
      " discount ": [
        "no discount"
      ]
    },
    "Kebabs & Curries": {
      " url ": "https://www.zomato.com/ncr/kebabs-curries-greater-kailash-gk-1-new-delhi",
      " location ": " G-14, Bhanot Corner, R Block, Greater Kailash 1 (GK 1), New Delhi",
      " rating ": [
        "3.8"
      ],
      " facility ": [
        "Just Delivery"
      ],
      " cuisines ": [
        "North Indian",
        "Mughlai",
        "Kebab"
      ],
      " cost_for_two ": "750",
      " hour ": "11:50am \u2013 11:30pm (Mon-Sat),11:30am \u2013 11:30pm (Sun)",
      " featured ": [
        "Just Delivery"
      ],
      " discount ": [
        "no discount"
      ]
    },
    "24 Hours": {
      " url ": "https://www.zomato.com/ncr/24-hours-rohini-new-delhi",
      " location ": " Sector 2, Rohini, New Delhi",
      " rating ": [
        "3.2"
      ],
      " facility ": [],
      " cuisines ": [
        "Chinese",
        "North Indian",
        "Continental"
      ],
      " cost_for_two ": "400",
      " hour ": "24 Hours (Mon-Sun)",
      " featured ": [],
      " discount ": [
        "35% off on all orders above \u20b9199"
      ]
    },
    "Bikaner Sweets": {
      " url ": "https://www.zomato.com/ncr/bikaner-sweets-krishna-nagar",
      " location ": " Shop 50, Khureji Khas, Krishna Nagar, New Delhi",
      " rating ": [
        "3.6",
        "3.2"
      ],
      " facility ": [],
      " cuisines ": [
        "Mithai",
        "Chinese",
        "South Indian"
      ],
      " cost_for_two ": "200",
      " hour ": "9am \u2013 10pm (Mon, Tue, Wed, Thu, Sun), 9:01am \u2013...",
      " featured ": [],
      " discount ": [
        "no discount"
      ]
    },
    "Fried Chicken Shack": {
      " url ": "https://www.zomato.com/ncr/fried-chicken-shack-janakpuri-new-delhi",
      " location ": " G-28, Vardhaman Janak Market, A2-B, Janakpuri, New Delhi",
      " rating ": [
        "3.9"
      ],
      " facility ": [],
      " cuisines ": [
        "Fast Food"
      ],
      " cost_for_two ": "400",
      " hour ": "11am \u2013 10pm (Mon-Sun)",
      " featured ": [],
      " discount ": [
        "no discount"
      ]
    },
    "Prince of China": {
      " url ": "https://www.zomato.com/ncr/prince-of-china-kalkaji-new-delhi",
      " location ": " 31-A, Krishna Market, Opposite Deshbandhu College, Kalkaji, New Delhi",
      " rating ": [
        "3.8"
      ],
      " facility ": [],
      " cuisines ": [
        "Chinese",
        "Seafood",
        "Thai"
      ],
      " cost_for_two ": "800",
      " hour ": "11:30am \u2013 11pm (Mon-Sun)",
      " featured ": [],
      " discount ": [
        "no discount"
      ]
    },
    "Cake Time": {
      " url ": "https://www.zomato.com/ncr/cake-time-kalkaji-new-delhi",
      " location ": " J 3/143 DDA, Kalkaji, New Delhi",
      " rating ": [
        "4.3"
      ],
      " facility ": [],
      " cuisines ": [
        "Bakery",
        "Fast Food"
      ],
      " cost_for_two ": "300",
      " hour ": "10am \u2013 10:30pm (Mon-Sun)",
      " featured ": [],
      " discount ": [
        "no discount"
      ]
    },
    "New Durga Corner": {
      " url ": "https://www.zomato.com/ncr/new-durga-corner-paschim-vihar-new-delhi",
      " location ": " Shop 3, A-5B, DDA Market, Paschim Vihar, New Delhi",
      " rating ": [
        "3.8",
        "4.1"
      ],
      " facility ": [],
      " cuisines ": [
        "South Indian"
      ],
      " cost_for_two ": "300",
      " hour ": "10am \u2013 10:30pm (Mon-Sun)",
      " featured ": [],
      " discount ": [
        "10% off on all orders above \u20b999"
      ]
    },
    "Pizza King Express": {
      " url ": "https://www.zomato.com/ncr/pizza-king-express-1-ballabhgarh-faridabad",
      " location ": " Plot 17, B Block, 33 Feet Road, Bhagat Singh Colony, Ballabhgarh, Faridabad",
      " rating ": [
        "3.8",
        "4.0"
      ],
      " facility ": [],
      " cuisines ": [
        "Pizza",
        "Fast Food"
      ],
      " cost_for_two ": "400",
      " hour ": "10am \u2013 10pm (Mon-Sun)",
      " featured ": [],
      " discount ": [
        "no discount"
      ]
    },
    "Shri Rama Restaurant": {
      " url ": "https://www.zomato.com/ncr/shri-rama-restaurant-karol-bagh-new-delhi",
      " location ": " 21-B/1, New Rohtak Road, Karol Bagh, New Delhi",
      " rating ": [
        "3.8",
        "3.9"
      ],
      " facility ": [],
      " cuisines ": [
        "North Indian",
        "Chinese",
        "Mughlai"
      ],
      " cost_for_two ": "550",
      " hour ": "12noon \u2013 4:30pm, 6:30pm \u2013 12midnight (Mon-Sun)",
      " featured ": [],
      " discount ": [
        "no discount"
      ]
    },
    "Shakespeer": {
      " url ": "https://www.zomato.com/ncr/shakespeer-rohini-new-delhi",
      " location ": " Shop B-2/1, Sector 18, Rohini, New Delhi",
      " rating ": [
        "3.6",
        "3.3"
      ],
      " facility ": [],
      " cuisines ": [
        "Cafe",
        "Beverages",
        "Sandwich",
        "Fast Food"
      ],
      " cost_for_two ": "300",
      " hour ": "11am \u2013 12midnight (Mon-Sun)",
      " featured ": [],
      " discount ": [
        "no discount"
      ]
    }
  }
]